Workbook

Sheet Title & PRISMA

Sheet Structure of Paper

Sheet Databases & Years
A1: Database Screening (17/4/2026) | B1: # Studies Identified | C1: # Studies Pass Duplicates Discard | D1: # Studies Pass Screening (Stage 1) | E1: # Studies Pass Screening 2 (Stage 2) | F1: # Studies Pass Eligibility Assessment | G1: # Studies Included | H1: Conference | I1: Journal
A2: Web of Science | B2: 282 | C2: 162 | D2: 83 | E2: 83 | F2: 34 | G2: 34 | H2: 11 | I2: 23
A3: Scopus | B3: 443 | C3: 192 | D3: 93 | E3: 93 | F3: 41 | G3: 41 | H3: 26 | I3: 15
A4: IEEE Xplore | B4: 49 | C4: 40 | D4: 38 | E4: 38 | F4: 26 | G4: 26 | H4: 9 | I4: 17
A5: ScienceDirect | B5: 18 | C5: 18 | D5: 18 | E5: 18 | F5: 15 | G5: 15 | H5: 0 | I5: 15
A6: ACM DL | B6: 52 | C6: 51 | D6: 6 | E6: 2 | F6: 2 | G6: 2 | H6: 1 | I6: 1
A7: Total | B7: =SUM(B2:B6) -> 844 | C7: =SUM(C2:C6) -> 463 | D7: =SUM(D2:D6) -> 238 | E7: =SUM(E2:E6) -> 234 | F7: =SUM(F2:F6) -> 118 | G7: =SUM(G2:G6) -> 118 | H7: =SUM(H2:H6) -> 47 | I7: =SUM(I2:I6) -> 71
A11: Database
A12: Web of Science | B12: 0.2881 | C12: Conference | D12: 11
C13: Journal | D13: 23
A14: Scopus | B14: 0.3475 | C14: Conference | D14: 26
C15: Journal | D15: 15
A16: IEEE Xplore | B16: 0.2203 | C16: Conference | D16: 9
C17: Journal | D17: 17
A18: Science Direct | B18: 0.1271 | C18: Conference | D18: 0
C19: Journal | D19: 15
A20: ACM DL | B20: 0.017 | C20: Conference | D20: 1
C21: Journal | D21: 1
A35: Quality Score | B35: Number of Publication
A36: 1 | B36: 0
A37: 1.25 | B37: 1
A38: 1.5 | B38: 0
A39: 1.75 | B39: 4
A40: 2 | B40: 5
A41: 2.25 | B41: 6
A42: 2.5 | B42: 14
A43: 2.75 | B43: 12
A44: 3 | B44: 7
A45: 3.25 | B45: 16
A46: 3.5 | B46: 21
A47: 3.75 | B47: 30
... A52: 5 | B52: 5
A57: Publication trends
A58: Year | B58: Included
A59: 2022 | B59: 1
A60: 2023 | B60: 4
A61: 2024 | B61: 29
A62: 2025 | B62: 61
A63: 2026 | B63: 23
A65: Year | B65: Google Scholar
A66: 2022 | B66: 229
A67: 2023 | B67: 547
A68: 2024 | B68: 1060
A69: 2025 | B69: 1810
A70: 2026 | B70: 890
A86: No. | B86: Publication venue | C86: Count | E86: Publisher | F86: Count
A87: 1 | B87: Neurocomputing | C87: 9 | E87: IEEE | F87: 44
A88: 2 | B88: Neural Networks | C88: 5 | E88: Elsevier | F88: 20
A89: 3 | B89: AAAI Conference on Artificial Intelligence | C89: 5 | E89: MDPI | F89: 9
A90: 4 | B90: Frontiers in Neuroscience | C90: 5 | E90: Association for the Advancement of Artificial Intelligence | F90: 8
A91: 5 | B91: IEEE Access | C91: 4 | E91: ACM | F91: 7
A92: 6 | B92: International Conference on Learning Representations | C92: 4 | E92: Frontiers | F92: 6
A93: 7 | B93: IEEE/CVF Conference on Computer Vision and Pattern Recognition, CVPR 2025 | C93: 3 | E93: NeurIPS | F93: 4
A94: 8 | B94: IEEE Internet of Things Journal | C94: 3 | E94: International Conference on Learning Representations | F94: 4
A95: 9 | B95: IEEE Transactions on Cognitive and Developmental Systems | C95: 3 | E95: Springer Nature | F95: 3
A96: 10 | B96: ACM International Conference on Multimedia | C96: 3 | E96: IJCAI | F96: 3
E97: PMLR | F97: 2
E98: IOP Publishing | F98: 2
E99: Anhalt University of Applied Sciences | F99: 1
E100: British Machine Vision Association | F100: 1
E101: Transactions on Machine Learning Research | F101: 1
E102: Public Library of Science | F102: 1
E103: International Speech Communication Association | F103: 1
E104: Wiley | F104: 1
A144: Country | B144: Number of publications
A145: China | B145: 94
A146: United States | B146: 8
A147: South Korea | B147: 3
A148: United Kingdom | B148: 3
A149: India | B149: 2
A150: Saudi Arabia | B150: 1
A151: Italy | B151: 1
A152: Iraq | B152: 1
A153: France | B153: 1
A154: Czechia | B154: 1
A155: Spain | B155: 1
A156: Malaysia | B156: 1
A157: United Arab Emirates | B157: 1
A159: Rank | B159: University | C159: Number of publications | D159: Year Started
A160: 1 | B160: University of Electronic Science and Technology of China | C160: 12 | D160: 2023
A161: 2 | B161: Peking University | C161: 11 | D161: 2023
A162: 3 | B162: Chinese Academy of Sciences | C162: 8 | D162: 2023
A163: 4 | B163: Harbin Institute of Technology | C163: 5 | D163: 2024
A164: 5 | B164: Shanghai University | C164: 4 | D164: 2024
A165: 6 | B165: Tsinghua University | C165: 4 | D165: 2024
A166: 7 | B166: Zhejiang University | C166: 4 | D166: 2024
A167: 8 | B167: Dalian University of Technology | C167: 3 | D167: 2022
A168: 9 | B168: University of California | C168: 3 | D168: 2024
A169: 10 | B169: Beijing Institute of Technology | C169: 2 | D169: 2024
A180: Application Domain | B180: Count
A181: Event-Based / Neuromorphic Vision | B181: 39
A182: Neuromorphic Hardware and Edge AI Acceleration | B182: 16
A183: Computer Vision and Image Understanding | B183: 14
A184: Robotics, Autonomous Systems, and UAV Vision | B184: 10
A185: Biomedical and Healthcare Signal Processing | B185: 10
A186: Speech, Audio, and Auditory Processing | B186: 8
A187: Communication, Cybersecurity, and Network Intelligence | B187: 7
A188: Industrial Monitoring, Fault Diagnosis, and Infrastructure Inspection | B188: 6
A189: Natural Language Processing and Language Models | B189: 5
A190: Remote Sensing, Geospatial, and Environmental Monitoring | B190: 3
...

Sheet Master Table Description
A1: Column | B1: Field Name | C1: Description / What to Extract
A2: A | B2: Paper ID | C2: Unique identifier for each paper, e.g., P001, P002, P003.
A3: B | B3: Full Citation | C3: Complete citation including authors, year, title, venue, volume/issue, pages, and article number where available.
A4: C | B4: Title | C4: Paper title
A5: D | B5: University | C5: Institution
A6: E | B6: Country | C6: Country
A7: F | B7: Publication Year | C7: Year the paper was published, accepted, or made available online.
A8: G | B8: Publication Venue | C8: Name of the journal, conference, workshop, book series, or preprint server.
A9: H | B9: Publisher | C9: Publishing body, e.g., IEEE, Elsevier, Springer, ACM, Frontiers, MDPI, AAAI, IJCAI, arXiv.
A10: I | B10: DOI / URL | C10: DOI, official publisher link, arXiv link, or stable URL.
A11: J | B11: Publication Type | C11: Journal article, conference paper, workshop paper, review paper, book chapter, or preprint.
A12: K | B12: Database Source | C12: Source from which the paper was retrieved (Scopus, Web of Science, IEEE Xplore, ACM DL, ScienceDirect, SpringerLink)
... A61: BH | B61: RQ Mapping | C61: Map the paper to your RQs using: Primary: RQx; Secondary: RQx, RQx.

Sheet Master Table
A1: Paper ID | B1: Full Citation | C1: Title | D1: University | E1: Country | F1: Publication Year | G1: Publication Venue | H1: Publisher | I1: DOI / URL | J1: Publication Type | K1: Database Source | L1: Paper Category | M1: E&QA Score | N1: Application Domain | O1: Specific Task | P1: Data Modality | Q1: Signal Dimensionality | R1: Signal Characteristics | S1: Dataset Name | T1: Dataset Type | U1: Dataset Size | V1: Dataset Balance / Split | W1: Hybrid Topology | X1: SNN Component | Y1: Neuron Model | Z1: Transformer Component | AA1: Attention Type | AB1: SNN–Transformer Interface Mechanism | AC1: Model Depth / Scale | AD1: Parameter Count | AE1: Design / Contribution Type | AF1: Input Encoding Method | AG1: Encoding Parameters | AH1: Encoding Learned or Fixed | AI1: Event / Spike Representation | AJ1: Temporal Resolution | AK1: Output Decoding Method | AL1: Encoding / Temporal Information Analysis | AM1: Training Paradigm | AN1: Training Method | AO1: Surrogate Gradient Function | AP1: ANN-to-SNN Conversion Method | AQ1: Optimizer | AR1: Loss Function | AS1: Training Hyperparameters | AT1: Primary Performance Metric | AU1: Primary Metric Value | AV1: Secondary Metrics | AW1: Baseline Models Compared | AX1: Performance Gain Over Baseline | AY1: Statistical Validation | AZ1: Ablation Study | BA1: Training Framework / Code Availability | BB1: Target Hardware | BC1: Hardware Deployment Status | BD1: Energy Evidence | BE1: Latency / Memory / Complexity Evidence | BF1: Comparison with ANN Baseline | BG1: Main Contribution / Key Limitation | BH1: RQ Mapping
A2: P001 | B2: Xu, B., Yin, Y., Iyer, V., & Li, P. (2025). Bishop: Sparsified Bundling Spiking Transformers on Heterogeneous Cores with Error-constrained Pruning. In Proceedings of the 52nd Annual International Symposium on Computer Architecture (ISCA ’25), June 21–25, 2025, Tokyo, Japan. ACM, New York, NY, USA, 14 pages. https://doi.org/10.1145/3695053.3731063 | C2: Bishop: Sparsified Bundling Spiking Transformers on Heterogeneous Cores with Error-constrained Pruning | D2: University of California | E2: United States | F2: 2025 | G2: Proceedings of the 52nd Annual International Symposium on Computer Architecture, ISCA ’25 | H2: ACM | I2: https://doi.org/10.1145/3695053.3731063 | J2: Conference paper | K2: ACM Digital Library | L2: Hardware-focused | M2: 4.5 | N2: Neuromorphic Hardware and Edge AI Acceleration | O2: Efficient inference acceleration for spiking Transformer workloads on image, event-based gesture, and speech-command recognition benchmarks | P2: Static images, event-camera/DVS data, and speech-command data | Q2: 2D image/token sequences; 2D spatiotemporal event data; sequence-based speech-command tokens | R2: CIFAR images are 32 × 32 and split into 64 tokens; ImageNet-100 images are 224 × 224 and split into 196 tokens; DVS-Gesture input is 128 × 128 and split into 64 tokens; models use 4–20 timesteps depending on dataset | S2: CIFAR10, CIFAR100, ImageNet-100, DVS-Gesture-128, Google Speech Command V2 | T2: Public benchmark datasets | U2: NR | V2: NR | W2: Spiking Transformer workload accelerated through a dedicated HW/SW co-design framework; model uses spiking tokenizer, multi-head spiking self-attention, spiking MLP blocks, and LIF-based spike processing | X2: LIF neurons, spiking tokenizer, spiking MLP, spiking Q/K/V projections, spike generator, binary spike activations | Y2: LIF | Z2: Multi-head Spiking Self-Attention block, residual encoder blocks, Q/K/V/O projection layers, spiking MLP block | AA2: Multi-head spiking self-attention; binary Q/K/V attention; softmax-free spiking attention | AB2: Spiking tokenizer converts input into T × N × D spiking token representation; LIF layers generate spike-form Q/K/V; Token-Time Bundle represents spiking tokens across time for hardware processing | AC2: Model 1: CIFAR10, 4 blocks, T=10, N=64, D=384; Model 2: CIFAR100, 4 blocks, T=8, N=64, D=384; Model 3: ImageNet-100, 8 blocks, T=4, N=196, D=128; Model 4: DVS-Gesture, 2 blocks, T=20, N=64, D=128; Model 5: Google SC, 4 blocks, T=8, N=256, D=384 | AD2: NR | AE2: New accelerator architecture and HW/SW co-design framework; Token-Time Bundle representation; heterogeneous dense/sparse/attention cores; Bundle-Sparsity Aware training; Error-Constrained TTB Pruning | AF2: Spiking tokenizer / token-based spiking representation; exact spike encoding rule for each dataset is NR | AG2: Timesteps: 4–20 depending on dataset; token counts: 64, 196, or 256; feature dimensions: 128 or 384; TTB bundle parameters BSt and BSn explored | AH2: NR | AI2: Binary spike tensor; spiking activations arranged as Token-Time Bundles; binary spiking Q/K/V; active and inactive TTBs | AJ2: 4 timesteps for ImageNet-100, 8 for CIFAR100 and Google Speech Command, 10 for CIFAR10, 20 for DVS-Gesture | AK2: Global average pooling across tokens and time followed by a linear prediction layer; hardware spike generator produces binary spike outputs | AL2: Yes. The paper analyzes spatiotemporal sparsity, Token-Time Bundle sparsity, active/inactive bundle distribution, bundle size sensitivity, and pruning effects on attention computation | AM2: Supervised learning for benchmark classification models; HW/SW co-design training pipeline | AN2: Bundle-Sparsity Aware training and ECP-aware training; loss combines cross-entropy with bundle-level sparsity loss | AO2: NR | AP2: N/A | AQ2: NR | AR2: Cross-entropy loss plus bundle-level sparsity regularization: Ltot = LCE + λLbsp | AS2: Batch size 256 and 300 epochs for CIFAR and ImageNet-100; batch size 64 and 100 epochs for DVS-Gesture; λ = 1 for CIFAR10, 0.5 for CIFAR100, 0.3 for ImageNet, 1.0 for DVS-Gesture; ECP pruning threshold 10 for DVS-Gesture and 6 for other models | AT2: Latency speedup and energy efficiency improvement | AU2: Average 5.91× speedup and 6.11× energy-efficiency improvement over PTB SNN accelerator; 299× average speedup over NVIDIA Jetson Nano edge GPU | AV2: Accuracy, chip area, power, latency, energy dissipation, EDP, pruning ratio, memory access reduction, attention-layer speedup | AW2: NVIDIA Jetson Nano edge GPU; Parallel Time Batching SNN accelerator; PTB; comparison also includes ANN and SNN accuracy references in background | AX2: Bishop+BSA+ECP achieves up to 7.73× speedup over PTB on ImageNet-100 and 4.06× on DVS-Gesture; attention core reduces latency by 10.7–23.3× and gives 1.39–1.96× energy saving over PTB | AY2: Benchmark-based evaluation and cycle-accurate hardware simulation; no repeated runs, standard deviation, confidence interval, or significance test reported | AZ2: Full. Includes BSA effect, ECP threshold analysis, stratification strategy, TTB bundle volume sensitivity, hardware area/power breakdown, and latency/energy comparisons | BA2: PyTorch-based training flow; CACTI 7.0 for memory energy estimation; STONNE simulator for sparse core simulation; code availability NR | BB2: Dedicated heterogeneous ASIC-style accelerator; 28 nm CMOS synthesis; dense core, sparse core, attention core, spike generator, GLB/DRAM memory hierarchy | BC2: RTL synthesis and cycle-accurate simulation; no fabricated chip or real neuromorphic hardware deployment reported | BD2: Estimated energy using CACTI 7.0, DRAM power model, RTL synthesis, and cycle-accurate accelerator simulation; not measured from fabricated silicon | BE2: Reports 2.96 mm² die area, 627 mW peak power, 500 MHz clock; 144 KB weight GLB; two 12 KB spike TTB GLBs; reports latency, energy, EDP, memory access, and attention computation reduction | BF2: Yes. Uses NVIDIA Jetson Nano edge GPU as an ANN hardware baseline and includes ANN/SNN accuracy comparison table, but the main efficiency comparison is against PTB SNN accelerator | BG2: Contribution: first dedicated hardware accelerator and HW/SW co-design framework for spiking Transformers using Token-Time Bundles, heterogeneous cores, BSA training, and ECP pruning. Limitation: evaluation is based on simulation and RTL synthesis, not fabricated hardware; dataset focus is mainly classification benchmarks | BH2: Primary: RQ5; Secondary: RQ2, RQ3, RQ4
A3: P002 | B3: Zhou, Y., Yin, H., Tan, C., Wu, Q., Sun, C., & Hong, R. (2026). An Efficient Hybrid Cascade Tracker with Spiking Neural Networks for Event Domain Tracking. ACM Transactions on Multimedia Computing, Communications, and Applications, 22(3), Article 75, 20 pages. https://doi.org/10.1145/3795518 | C3: An Efficient Hybrid Cascade Tracker with Spiking Neural Networks for Event Domain Tracking | D3: Anhui University | E3: China | F3: 2026 | G3: ACM Transactions on Multimedia Computing, Communications, and Applications | H3: ACM | I3: https://doi.org/10.1145/3795518 | J3: Journal article | K3: ACM Digital Library | L3: Application-focused | M3: 4.5 | N3: Event-Based / Neuromorphic Vision | O3: Single object tracking / bounding-box prediction in event streams | P3: Event-camera data; simulated event data from RGB frame datasets | Q3: 2D spatiotemporal event representation; event voxel/grid-style frame representation | R3: Event stream represented as quadruples (x, y, t, p) with spatial location, timestamp, and polarity; events between adjacent frames are aggregated into an n-bin voxel grid with positive and negative polarity frames | S3: VisEvent, FE108, COESOT, Event-OTB, Event-VOT | T3: Public event-based tracking benchmarks; simulated event datasets converted from RGB tracking benchmarks | U3: VisEvent: 820 videos / 371,127 frames; FE108: 108 videos / 208,672 frames; COESOT: 1,354 videos / 478,721 frames; OTB100/Event-OTB: 100 videos / 59,040 frames; VOT2019/Event-VOT: 60 videos / 19,935 frames | V3: Uses public benchmark training/testing protocols; exact class/object balance NR | W3: Parallel/cascade hybrid CNN–SNN–Transformer topology; EHCT uses repeated HCST blocks containing C-SNN and T-SNN branches, connected by a T2C Adapter and fused by CTFM | X3: C-SNN branch, T-SNN branch, LIF layers, spike-based self-attention, spike-based MLP, spike-driven temporal encoding | Y3: LIF | Z3: Transformer-SNN encoder block; spike-based self-attention; spike-based MLP; T-SNN branch | AA3: Spike-based self-attention; scaled dot-product attention in CTFM fusion module | AB3: Q and K are projected then converted into spike sequences using LIF neurons; spike-form Q and K allow dot-product computation through logical AND and summation; T2C Adapter concatenates T-SNN and C-SNN outputs, applies 1 × 1 convolution, then LIF for spike-form compatibility | AC3: HCST block number N tested from 1 to 5; final model uses N = 3 HCST blocks; T-SNN can be stacked by N layers | AD3: NR | AE3: New event-domain hybrid cascade tracker; HCST block; C-SNN and T-SNN dual-branch design; T2C Adapter; CTFM fusion module | AF3: Event-to-frame / voxel-grid representation; events between adjacent frames are aggregated into n bins and separated into positive and negative polarity frames | AG3: Event tuple (x, y, t, p); n-bin voxel grid; positive and negative event frames; timestep T = 5 for SNN energy analysis; LIF threshold h = 1.0; leakage factor uses τ = 2.0 | AH3: Fixed event representation; feature fusion and projection layers are learned | AI3: Event frames, positive/negative polarity frames, spike sequences, spike-form Q and K, LIF spike activations | AJ3: Event cameras provide microsecond-level temporal resolution; SNN timestep T = 5 in energy analysis | AK3: Classifier and regressor heads produce the tracking bounding box | AL3: Partial. The paper analyzes event sparsity, firing rate of LIF layers, spike-driven temporal encoding, and feature visualizations, but does not deeply quantify temporal information loss | AM3: Supervised learning within Siamese tracking framework | AN3: Surrogate-gradient direct training using SpikeJelly; SiamFC++/STNet-style tracking loss framework | AO3: ATan surrogate gradient | AP3: N/A | AQ3: Stochastic Gradient Descent | AR3: Follows SiamFC++ and STNet tracking loss; exact full loss formula NR | AS3: Batch size 32; trained on NVIDIA RTX 3090 GPUs; backbone frozen in first epoch; backbone learning rate 0.1 from epoch 2; other components use learning rate 0.001 to 0.01 during epochs 1–5 then decay 10× every 5 epochs; SGD momentum 0.9; weight decay 5e-5; LIF threshold h = 1.0; τ = 2.0 | AT3: Success Rate, Precision Rate, Overlap Precision | AU3: VisEvent: SR 39.6, OP0.50 46.5, OP0.75 25.6, PR 55.5; FE108: SR 54.5, OP0.50 69.0, OP0.75 22.9, PR 85.1; COESOT: SR 45.1, OP0.50 53.9, OP0.75 27.2, PR 52.2 | AV3: Normalized Precision Rate, FPS, firing rate, theoretical energy consumption | AW3: ATOM, DiMP, PrDiMP, TransT, ToMP, STARK, MixFormer, MDNet, CEUTrack, HDETrack, FENet, STNet, DANet, AFNet, HiT, FERMT | AX3: On VisEvent, EHCT achieves best PR 55.5 and OP0.50 46.5; on FE108, EHCT achieves best SR 54.5 and PR 85.1; on Event-OTB and Event-VOT, EHCT outperforms CEUTrack, STNet, AFNet, and HDETrack in SR and PR | AY3: Public benchmark evaluation and ablation experiments; no standard deviation, confidence interval, repeated-run analysis, or significance test reported | AZ3: Full. Includes C-SNN vs T-SNN branches, with/without SNN, T2C Adapter variants, CTFM variants, number of HCST blocks, lightweight backbone, and single-block variants | BA3: PyTorch; SpikingJelly; source code stated to be available at GitHub: masac11/EHCT | BB3: GPU/CPU for implementation; future neuromorphic hardware and embedded platforms mentioned | BC3: Evaluated on PC/GPU; no real neuromorphic hardware deployment reported | BD3: Theoretical energy estimate using SOP, firing rate, timestep, FLOPs, MAC energy 4.6 pJ, and AC energy 0.9 pJ; average firing rate about 2.1567%; claims approximately 45× energy efficiency over ANN with same structure | BE3: EHCT runs at 95 FPS on VisEvent; inference requires 2 GB GPU memory and 5 GB CPU RAM; lightweight variants report up to 111 FPS but lower accuracy | BF3: Yes. Compares with RGB/ANN-based trackers such as ATOM, DiMP, PrDiMP, TransT, ToMP, STARK, MixFormer, MDNet, HiT, and FERMT | BG3: Contribution: proposes EHCT, a hybrid CNN–SNN–Transformer tracker for event-domain object tracking, using HCST blocks, T2C Adapter, and CTFM fusion to combine local spike features and global Transformer context. Limitation: struggles under extreme fast motion and long occlusion; energy evidence is theoretical and no real neuromorphic deployment is reported | BH3: Primary: RQ1; Secondary: RQ2, RQ3, RQ4, RQ5
A4: P003 | B4: Alohali, M. A., Saleem, N., Rhouma, D., Medani, M., Elmannai, H., & Bourouis, S. (2024). Temporally Dynamic Spiking Transformer Network for Speech Enhancement. IEEE Access, 12, 146513–146526. https://doi.org/10.1109/ACCESS.2024.3444596 | C4: Temporally Dynamic Spiking Transformer Network for Speech Enhancement | D4: Princess Nourah Bint Abdulrahman University | E4: Saudi Arabia | F4: 2024 | G4: IEEE Access | H4: IEEE | I4: https://doi.org/10.1109/ACCESS.2024.3444596 | J4: Journal article | K4: IEEE Xplore | L4: Application-focused | M4: 4 | N4: Speech, Audio, and Auditory Processing | O4: Single-channel speech enhancement / noisy speech reconstruction | P4: Audio signal represented as complex spectrogram | Q4: 1D temporal speech waveform converted to 2D time-frequency spectrogram | R4: Input is real and imaginary parts of noisy spectrogram, Y ∈ R(2×T×F); sampling rate 16 kHz; STFT window length 512 samples; frame shift 16 ms | S4: WSJ0-SI84; VCTK+DEMAND | T4: Public benchmark speech enhancement datasets | U4: WSJ0-SI84: 3000 training utterances, 1000 test utterances, approximately 150 hours of training mixtures; VCTK+DEMAND: 11,572 training mixtures and 824 test mixtures | V4: WSJ0-SI84: training utterances from 83 speakers, testing from unseen speakers; SNR −5 dB to 5 dB for training and −3, 0, 3, 6 dB for testing. VCTK+DEMAND: 28 training speakers, 2 test speakers; training SNRs 0, 5, 10, 15 dB; testing SNRs 2.5, 7.5, 12.5, 17.5 dB | W4: CNN encoder-decoder with a dual-branch Spiking Transformer Network bottleneck | X4: Spike neuron layers, spike-based Q/K/V, spiking self-attention, spiking Transformer encoder | Y4: NR | Z4: Spiking Transformer Network bottleneck, spiking self-attention, MLP block, temporal attention branch, frequency attention branch | AA4: Spiking self-attention; temporal attention; frequency attention | AB4: Q, K, and V are first generated using learnable matrices and batch normalization, then transformed into spike sequences through spike neuron layers; spike-based Q/K/V are used in the self-attention computation | AC4: Encoder has four convolutional layers with multi-scale feature blocks; decoder mirrors encoder with four sub-pixel deconvolutional layers; bottleneck uses dual-branch STN | AD4: 3.14 million parameters | AE4: New application architecture combining convolutional encoder-decoder, multi-scale feature extraction, and dual-branch Spiking Transformer bottleneck for speech enhancement | AF4: Complex spectrogram input; real and imaginary parts of noisy speech spectrogram are processed by CNN encoder, then STN converts projected features into spike-based Q/K/V | AG4: Sampling rate 16 kHz; window length 512 samples; frame shift 16 ms; spike Q/K/V generated through spike neuron layers; α and β adaptive branch weights initialized as 1 | AH4: Partially learned: spectrogram extraction is fixed, while Q/K/V projections and branch weights are learned | AI4: Spike sequences for Q, K, and V; spike-based attention representations with binary 0/1 spike values | AJ4: Frame shift 16 ms; temporal frames T in spectrogram; exact SNN timestep NR | AK4: Decoder outputs real and imaginary components of the estimated clean spectrum, followed by inverse STFT to reconstruct waveform | AL4: Partial. The paper discusses temporal/spectral dependency modeling and visualizes spectrogram quality, but does not deeply analyze spike encoding information loss or spike temporal preservation | AM4: Supervised learning | AN4: Direct end-to-end training of CNN encoder-decoder with Spiking Transformer bottleneck | AO4: NR | AP4: N/A | AQ4: Adam | AR4: Weighted spectro-temporal loss: L = υLtime + (1−υ)Lfrequency, with υ = 0.4 | AS4: Batch size 16; 100 epochs; Adam with α = 0.001, β1 = 0.9, β2 = 0.999, ε = 10⁻⁸; learning rate starts at 0.001 and decays to 0.0005, 0.0002, and 0.0001; dropout 0.20 | AT4: PESQ, ESTOI, SI-SDR | AU4: WSJ0-SI84 seen condition average: ΔSI-SDR = 11.52 dB, ΔESTOI = 39.67%, ΔPESQ = 1.22. VCTK+DEMAND: STOI = 95.0, PESQ = 3.13, SNRSeg = 11.12 | AV4: STOI, SNRSeg, FW-SNRSeg, Csig, Cbak, Covl, MACs, RTF, memory footprint | AW4: CRN, DPRNN, GCRN, DCCRN, AECNN, CTSNet, GaGNet, CPBNet, PHASEN, RDLNet, DEMUCS, TSTNN, MSSA-TCN, FAFNet, PFRNet, UTFAT, DBS4D, DBCRN, SADN-UNet, NSNet, DPT-FSNet, DPTGAN, DPT-ECA, FullSubNet+, FRCRN, DF-Net | AX4: On WSJ0-SI84, TD-STNet outperforms CRN by 3.83 dB ΔSI-SDR, 7.28% ΔESTOI, and 0.35 ΔPESQ. On VCTK+DEMAND, it improves over several baselines while keeping 3.14M parameters and 0.18 RTF | AY4: Benchmark evaluation on seen/unseen speakers and noises; no standard deviation, confidence interval, repeated-run analysis, or statistical significance test reported | AZ4: Full. Includes TD-STNet with traditional Transformer, without STN bottleneck, STN with only FAB, STN with only TAB, and full dual-branch STN | BA4: Framework NR; code availability NR | BB4: CPU/GPU evaluation; real-time speech enhancement setting | BC4: Evaluated computationally on CPU/GPU; no neuromorphic hardware deployment reported | BD4: No direct energy measurement; efficiency discussed through parameters, MACs, real-time factor, inference time, and memory footprint | BE4: 3.14M parameters; 9.64 G/s MACs; 0.18 RTF; approximately 10.12 MB memory; CPU processing time 0.20 s; PMFP 0.28 G; BMFP 0.29 G; training batch time 0.25 s | BF4: Yes. Compares against many ANN/CNN/RNN/Transformer-based speech enhancement baselines | BG4: Contribution: proposes TD-STNet, a convolutional encoder-decoder with dual-branch Spiking Transformer bottleneck for temporal and spectral speech enhancement. Limitation: attention only uses current input at each time step, underusing historical temporal information; no real neuromorphic hardware or measured energy evaluation | BH4: Primary: RQ1; Secondary: RQ2, RQ3, RQ4, RQ5
A5: P004 | B5: Fang, C., Shen, Z., Li, T., Zhao, S., Tian, F., Yang, J., & Sawan, M. (2025). A 28nm Spiking Vision Transformer Accelerator with Dual-Path Sparse Compute Core and EMA-free Self-Attention Engine for Embodied Intelligence. IEEE Transactions on Circuits and Systems for Artificial Intelligence. https://doi.org/10.1109/TCASAI.2025.3596210 | C5: A 28nm Spiking Vision Transformer Accelerator with Dual-Path Sparse Compute Core and EMA-free Self-Attention Engine for Embodied Intelligence | D5: Westlake University | E5: China | F5: 2025 | G5: IEEE Transactions on Circuits and Systems for Artificial Intelligence | H5: IEEE | I5: https://doi.org/10.1109/TCASAI.2025.3596210 | J5: Journal article | K5: IEEE Xplore | L5: Hardware-focused | M5: 4.5 | N5: Robotics, Autonomous Systems, and UAV Vision | O5: Real-time visual cortex acceleration for embodied intelligence tasks, including manipulation and navigation | P5: RGB image frames encoded into spike format | Q5: 2D image sequence / spatiotemporal visual input | R5: Uses three consecutive visual frames per inference; input resolutions include 256 × 256 and 128 × 128; RGB input is encoded into spike format with 8 timesteps | S5: CortexBench tasks; Adroit; MetaWorld; DeepMind Control; ObjectNav; ImageNav; HM3DSem; Gibson; Mujoco-based datasets | T5: Public embodied AI / robotic manipulation / navigation benchmark datasets | U5: NR | V5: NR | W5: Spiking Vision Transformer visual cortex accelerator; spiking tokenizer/encoder converts RGB input to spike format, followed by spiking Transformer blocks and an off-chip non-spiking policy MLP | X5: Spike encoder layer, spike-format feature maps, spiking Transformer blocks, spike-based Q/K/V, 1-bit spike activations | Y5: Spiking neurons used for input encoding; exact neuron model NR | Z5: Spiking Vision Transformer; spiking Transformer blocks; Spiking Self-Attention; ViT-B and ViT-L visual cortex models | AA5: Spiking self-attention; linear attention; softmax-free SSA | AB5: RGB frames are encoded into spike format with 8 timesteps; patch embeddings are processed by spiking Transformer blocks; Q, K, and V are represented as 1-bit spike matrices in SSA | AC5: ViT-B and ViT-L are mapped; typical target SSA setting uses N = 256 and head dimension d = 64; ideal hardware efficiency supports N ≤ 4096 and D ≤ 4096 | AD5: ViT-B: 86M parameters; ViT-L: 307M parameters | AE5: Fabricated 28nm Spiking Vision Transformer accelerator; dual-path sparse compute core; group-wise frame-differential dataflow; EMA-free SSA engine; first-order SSA approximation; KV-first dataflow; transpose engine; unified 1b/8b adder-tree array | AF5: RGB-to-spike encoding using an encoder layer with spiking neurons; group-wise frame-differential dataflow uses 1 raw frame and 2 differential frames | AG5: Spike timestep = 8; input group size = 3 frames; block-wise CSR compression for differential frames; 1-bit spike representation; INT8 precision for weights/operations | AH5: Partially learned: spike encoder layer is part of the model, while frame-differential dataflow and block-wise CSR compression are hardware/dataflow mechanisms | AI5: 1-bit spike feature maps; raw bitmaps for raw frames; block-wise CSR format for differential sparse frames; spike-based Q/K/V matrices | AJ5: 8 SNN timesteps; 3-frame temporal window for embodied intelligence inference | AK5: CLS tokens from three frame embeddings are extracted and concatenated, then passed to a 3-layer non-spiking policy MLP to generate the agent action | AL5: Yes. The paper analyzes input sparsity, frame-to-frame similarity, frame-differential sparsity, cosine similarity between approximated and exact SSA, and energy efficiency under different sparsity levels | AM5: Pretrained visual representation / embodied AI inference setting; exact SNN training paradigm NR | AN5: NR | AO5: NR | AP5: NR | AQ5: NR | AR5: NR | AS5: NR | AT5: Energy efficiency; energy per inference/frame; task latency; accuracy loss compared with INT8 ViT | AU5: Energy efficiency: 57.7 TOPS/W for manipulation, 51.7 TOPS/W for ObjectNav, 41.2 TOPS/W for ImageNav; energy per inference: 1.79 mJ for ViT-B and 3.78 mJ for ViT-L | AV5: FPS, EMA reduction, accuracy loss, sparsity, power, voltage/frequency scaling, die area, SRAM size, latency | AW5: Vanilla INT8 ViT models; SOTA ViT accelerators including VLSI’23, ISSCC’22, ISSCC’23, JSSC’24, and VLSI’24 processors | AX5: 58% input EMA reduction; 83.6% lower SSA memory space; 46.5% lower SSA computation latency; 4× faster 1-bit matrix multiplication with 19% area overhead; 4.1× lower energy than previous work with same model; 34.8% higher task-level energy efficiency than SOTA ViT accelerator | AY5: Hardware measurement across multiple EAI tasks; no standard deviation, confidence interval, or significance test reported | AZ5: Partial/full hardware ablation. Reports system-level performance with optimizations enabled/disabled, SSA approximation accuracy loss, cosine similarity analysis, sparsity-energy analysis, and area/power breakdown | BA5: Hardware implemented in 28nm CMOS; FPGA-based testing platform; code availability NR | BB5: Fabricated 28nm CMOS accelerator chip; FPGA-based test platform; RISC-V controller; 32 compute cores; 640KB SRAM | BC5: Fabricated and measured silicon chip; validated on real hardware test platform for EAI tasks | BD5: Measured chip power and energy using an independent power supply / Keysight B2902A DC power analyzer; reports energy per frame and TOPS/W including EMA | BE5: Die area 6.5 mm²; 640KB SRAM; 0.55–1.1V; 30–200 MHz; power 9.04–222.65 mW; task latency 29.76 ms for ViT-B and 62.77 ms for ViT-L; FPS 33.60, 15.93, and 81.43 across tasks | BF5: Yes. Compares accuracy loss against INT8 vanilla ViT and compares hardware efficiency against non-spiking ViT accelerators | BG5: Contribution: proposes and fabricates a 28nm Spiking Vision Transformer accelerator for embodied intelligence with dual-path sparse computation, EMA-free SSA, and unified 1b/8b adder-tree acceleration. Limitation: policy MLP remains off-chip on FPGA; evaluation focuses on embodied vision tasks rather than broader SNN–Transformer domains; training details are not reported | BH5: Primary: RQ5; Secondary: RQ2, RQ3
A6: P005 | B6: Fang, C., Shen, Z., Wang, Z., Wang, C., Zhao, S., Tian, F., Yang, J., & Sawan, M. (2025). An Energy-Efficient Unstructured Sparsity-Aware Deep SNN Accelerator With 3-D Computation Array. IEEE Journal of Solid-State Circuits, 60(3), 977–989. https://doi.org/10.1109/JSSC.2024.3507095 | C6: An Energy-Efficient Unstructured Sparsity-Aware Deep SNN Accelerator With 3-D Computation Array | D6: Westlake University | E6: China | F6: 2025 | G6: IEEE Journal of Solid-State Circuits | H6: IEEE | I6: https://doi.org/10.1109/JSSC.2024.3507095 | J6: Journal article | K6: IEEE Xplore | L6: Hardware-focused | M6: 4.5 | N6: Event-Based / Neuromorphic Vision | O6: Hardware acceleration of direct-trained deep SNNs, including Spikingformer and Spiking ResNet, for image classification and gesture recognition | P6: Static image data and dynamic vision sensor/event data | Q6: 2D image inputs converted to spike sequences; event/spike sequences with temporal timesteps | R6: Static images are encoded into spike format using one convolution layer and spiking neuron layer; DVS raw spike sequences are segmented into T = 8 timesteps and accumulated before re-encoding into spike format | S6: ImageNet, CIFAR-10, DVS-128 Gesture | T6: Public static image classification and dynamic vision/event-based gesture recognition benchmarks | U6: NR | V6: NR | W6: Spiking Transformer and Spiking ResNet workloads mapped to a fabricated sparse DSNN accelerator; Spiking Transformer uses spiking tokenizer, spiking Q/K/V generation, and spiking self-attention | X6: Spiking tokenizer, LIF neurons, spike-only operators, spiking convolution, spiking Q/K/V generation, spiking self-attention, single-bit spikes | Y6: LIF | Z6: Spiking Transformer / Spikingformer blocks; spiking tokenizer; S_QKV_Gen; spiking self-attention | AA6: Spiking self-attention; softmax-free spike attention | AB6: LIF neurons are placed before operators so that SCONV, linear layers, and attention receive 1-bit spike inputs; S_QKV_Gen converts input sequence X ∈ R(T×N×Dx) into spike-form Q, K, and V | AC6: Spikingformer-8-768: 8 Transformer blocks, hidden dimension 768; Spiking ResNet-9-32: 9 residual layers, 32 channels; timestep T = 8 | AD6: NR | AE6: Fabricated sparse DSNN accelerator with 3-D computation array, unstructured non-zero data fetcher, two-stage fan-in prioritized sparse dataflow, and multimode unified computation scheduler for SCONV, S_QKV_Gen, and SSA | AF6: Static images encoded into spike format by a convolution layer and spiking neuron layer; DVS event data segmented into T = 8 timesteps and accumulated, then encoded again using an additional convolution layer | AG6: Timestep T = 8; 8-bit weights; single-bit spike activations; two-stage bitmap format using global bitmap and local bitmap | AH6: Partially learned: the convolutional spike encoder is model-based, while two-stage bitmap compression and sparse scheduling are fixed hardware/dataflow mechanisms | AI6: Single-bit spike sequences; global bitmap for positions where all T spikes are zero/non-zero; local bitmap for timestep-level spike information; compressed spike bitmap format | AJ6: 8 timesteps for evaluated models | AK6: Classification output from mapped Spikingformer / Spiking ResNet models; exact classifier decoding details NR | AL6: Yes. The paper analyzes timestep-parallel processing, spike sparsity, per-layer sparsity, two-stage bitmap storage efficiency, and energy efficiency under different spike sparsity levels | AM6: Direct-trained SNN inference workloads; hardware paper does not train models directly | AN6: NR | AO6: NR | AP6: N/A for the evaluated direct-trained SNN setting | AQ6: NR | AR6: NR | AS6: NR | AT6: Energy efficiency; energy per spike operation; recognition accuracy | AU6: Best energy efficiency: 0.078 pJ/SOP; ImageNet accuracy using Spikingformer: 77.6% / 77.7%; ImageNet energy efficiency: 42.8 TOPS/W | AV6: TOPS/W, pJ/SOP, task energy, latency, peak performance, area efficiency, power, voltage/frequency scaling, spike sparsity, storage efficiency | AW6: SOTA SNN processors, sparse ANN processors, Spikingformer, Spiking ResNet, prior ISSCC/JSSC accelerators | AX6: 68.3% external memory access reduction from timestep-parallel dataflow; 78% SSA operation reduction using sparse attention skipper; 51.1% SCONV latency reduction from memory router; 1.75× higher ImageNet energy efficiency than SOTA SNN processors; 1.4× higher than sparse ANN processors | AY6: Hardware measurement and benchmark comparison; no standard deviation, confidence interval, or statistical significance testing reported | AZ6: Partial hardware ablation/analysis. Includes energy efficiency vs spike sparsity, storage efficiency comparison, load-balancer window-size analysis, per-layer energy/sparsity analysis, and operator-specific scheduling analysis | BA6: Fabricated 40-nm CMOS accelerator; FPGA-based testing platform; software/code availability NR | BB6: Fabricated 40-nm CMOS neuromorphic accelerator with 3 computation clusters, 9 sparse cores, 3-D computation arrays, FPGA test platform | BC6: Fabricated and measured silicon chip | BD6: Measured chip power using Keysight B2902A DC power analyzer; reports TOPS/W, pJ/SOP, task energy, and voltage/frequency scaling | BE6: Die area 1.54 × 1.46 mm² / 2.24 mm²; 192 KB SRAM; 50–200 MHz; 0.56–1.1 V; power 2.84–43.58 mW; peak performance 230.4 GOPS; best dense energy efficiency 20.28 TOPS/W without sparsity | BF6: Yes. Compares against sparse ANN processors and discusses ANN MAC baseline versus SNN AC-only processing | BG6: Contribution: proposes a fabricated 40-nm sparse DSNN accelerator that supports modern direct-trained Spiking Transformers and Spiking ResNets using timestep-parallel computation, non-zero spike fetching, and operator-specific scheduling. Limitation: focuses mainly on vision/image and DVS benchmarks; training details are not reported; first non-spiking convolution/preprocessing for DVS is implemented on FPGA rather than fully on-chip | BH6: Primary: RQ5; Secondary: RQ2, RQ3
A7: P006 | B7: Gao, Y., Wang, T., Yang, Y., Gong, L., Chen, X., Wang, C., Li, X., & Zhou, X. (2025). Advancing Neuromorphic Architecture Toward Emerging Spiking Neural Network on FPGA. IEEE Transactions on Computer-Aided Design of Integrated Circuits and Systems, 44(9), 3465–3478. https://doi.org/10.1109/TCAD.2025.3547275 | C7: Advancing Neuromorphic Architecture Toward Emerging Spiking Neural Network on FPGA | D7: University of Science and Technology of China | E7: China | F7: 2025 | G7: IEEE Transactions on Computer-Aided Design of Integrated Circuits and Systems | H7: IEEE | I7: https://doi.org/10.1109/TCAD.2025.3547275 | J7: Journal article | K7: IEEE Xplore | L7: Hardware-focused | M7: 4.5 | N7: Neuromorphic Hardware and Edge AI Acceleration | O7: Accelerating Transformer Spiking Neural Network inference on FPGA for CIFAR-10, CIFAR-100, and ImageNet classification | P7: Static image data converted into spike sequences | Q7: 2D image sequence represented as X ∈ R(T×C×H×W), then reshaped into spike patches I ∈ R(T×N×D) | R7: Input spikes are represented by 1-bit values; synapse weights are quantized to 8-bit; TSNN uses spike patches, channel dimension, timesteps, and LIF neuron dynamics | S7: CIFAR-10, CIFAR-100, ImageNet | T7: Public image classification benchmark datasets | U7: NR | V7: NR | W7: Transformer Spiking Neural Network accelerated by heterogeneous FPGA architecture; TSNN consists of spiking patch splitting, L-block spike encoder, spike-driven self-attention module, spike MLP module, shortcut connections, and classification head | X7: LIF spike neuron layers, binary spikes, spiking patch splitting, spike encoder, spike-driven self-attention, spike MLP, membrane shortcut | Y7: LIF | Z7: Transformer Spiking Neural Network; spike-driven self-attention; spike MLP; spike encoder blocks | AA7: Spike-driven self-attention using mask and accumulation operations | AB7: Spike neuron layers convert inputs into binary spike vectors; spike linear transformation generates Qs, Ks, and Vs; SDSA applies mask operations between Ks and Vs, accumulates along spike patches, then masks with Qs | AC7: CIFAR-10: 10.23M parameters, 9.88G mult-add, spike patches 64, channel 512, 2 blocks, 4 timesteps; CIFAR-100: 10.28M parameters, 9.88G mult-add, spike patches 64, channel 512, 2 blocks, 4 timesteps; ImageNet: 29.69M parameters, 66.09G mult-add, spike patches 196, channel 512, 8 blocks, 4 timesteps | AD7: CIFAR-10: 10.23M; CIFAR-100: 10.28M; ImageNet: 29.69M | AE7: FPGA-based neuromorphic architecture named SpikeTA; heterogeneous hardware engines; DSP-efficient addition tree; depth-aware buffer management; streaming dataflow mapping; split-engine dataflow mapping; latency-aware parallelism search | AF7: Spiking patch splitting converts image sequences into spike patch sequences; LIF spike neuron layers convert continuous inputs into spike sequences | AG7: 1-bit input spikes; 8-bit synapse weights; membrane threshold = 1.0; coefficient τ = 2.0; timestep = 4 for evaluated TSNN models | AH7: Partially learned: TSNN is trained/fine-tuned using backpropagation; hardware mapping/dataflow and quantization are fixed deployment mechanisms | AI7: Binary spike vectors; spike patches; Qs/Ks/Vs spike matrices; 1-bit spike inputs with 8-bit synaptic weights | AJ7: 4 timesteps | AK7: Classification head performs final image classification | AL7: Partial. The paper analyzes spike representation, LIF charging/firing/resetting, spike-driven MAAC computation, and hardware buffering/dataflow for timesteps, but does not deeply analyze temporal information preservation | AM7: Supervised direct training / fine-tuning of TSNN | AN7: Backpropagation training with surrogate function; quantization optimization within 10 epochs using the training recipe from Spike-driven Transformer | AO7: Sigmoid surrogate function | AP7: N/A | AQ7: NR | AR7: NR | AS7: PyTorch 2.3.1, CuPy 13.2, SpikingJelly 0.0.0.0.10, CUDA 12.4; quantization optimization within 10 epochs; training time about 11 min for CIFAR-10, 23 min for CIFAR-100, and 2 days for ImageNet on NVIDIA A100; threshold 1.0; τ = 2.0; 1-bit spikes; 8-bit weights | AT7: Architecture performance, speedup, energy efficiency, classification accuracy | AU7: Peak performance: 28.99 TOPs; end-to-end execution time: 1.11 s for CIFAR-10, 1.11 s for CIFAR-100, and 68.08 s for ImageNet; accuracy: 95.60% on CIFAR-10, 78.40% on CIFAR-100, and 74.56% on ImageNet | AV7: GOPs/W, power consumption, hardware utilization, FPGA resource utilization, DSP/LUT/BRAM/URAM usage, execution latency, performance speedup over CPU/GPU/accelerators | AW7: AMD EPYC 7542 CPU; NVIDIA A100 GPU; FireFly; DeepFire2; E3NE; HeatViT; SSR Transformer accelerator; other SNN and non-spiking Transformer accelerators | AX7: 140.73×–1023.53× speedup over AMD EPYC 7542 CPU; 2.97×–7.29× speedup over NVIDIA A100 GPU; 223.21×–2150.18× energy-efficiency gain over CPU; 6.41×–28.04× energy-efficiency gain over GPU; 2.79× over SOTA SNN accelerator; 2.66× over SOTA non-spiking Transformer accelerator | AY7: Benchmark and hardware comparison across three datasets; no standard deviation, confidence interval, repeated-run analysis, or statistical significance test reported | AZ7: Partial hardware ablation. Includes comparison of computing strategies SpikeTA-op1/op2/op3/final, hardware utilization analysis, resource utilization breakdown, and pipelined latency balancing analysis | BA7: PyTorch, CuPy, SpikingJelly, CUDA 12.4 for training; Xilinx Vitis HLS/Vivado for FPGA implementation; code availability NR | BB7: Xilinx Alveo U280 FPGA with xcu280-fsvh2892-2L-e chip; 9024 DSPs, 1304k LUTs, 2607k FFs, 2016 BRAMs, 960 URAMs, and 32 HBM channels | BC7: Implemented and evaluated on FPGA prototype using Vitis HLS and Vivado | BD7: Power measured using Xilinx Board Utility xbutil; reported power consumption is 70.93 W, 71.45 W, and 71.76 W on CIFAR-10, CIFAR-100, and ImageNet respectively; energy efficiency reported up to 403.99 GOPs/W | BE7: Clock frequency 450 MHz; uses three parallel hardware kernels across SLRs; end-to-end times of 1.11 s, 1.11 s, and 68.08 s; total hardware utilization about 91.87%–91.94%; resource use includes 61.87% URAM, 77.98% BRAM, 79.43% DSP, 8.87% LUTRAM, and 63.86% LUTCOM | BF7: Yes. Compares with non-spiking Transformer accelerators and CPU/GPU ANN-style execution baselines | BG7: Contribution: proposes SpikeTA, the first FPGA-based neuromorphic hardware architecture explicitly designed for TSNN acceleration, using heterogeneous hardware engines, DSP-efficient addition, depth-aware buffering, and optimized dataflow mapping. Limitation: evaluated only on image classification TSNN models; energy efficiency is FPGA-board based rather than ASIC silicon; adaptability to broader TSNN models is left for future work | BH7: Primary: RQ5; Secondary: RQ2, RQ3, RQ4
A8: P007 | B8: Guo, Y., Liu, X., Chen, Y., Peng, W., Zhang, Y., & Ma, Z. (2025). Spiking Transformer: Introducing Accurate Addition-Only Spiking Self-Attention for Transformer. In Proceedings of the IEEE/CVF Conference on Computer Vision and Pattern Recognition (CVPR 2025), pp. 24398–24408. https://doi.org/10.1109/CVPR52734.2025.02272 | C8: Spiking Transformer: Introducing Accurate Addition-Only Spiking Self-Attention for Transformer | D8: Peking University | E8: China | F8: 2025 | G8: IEEE/CVF Conference on Computer Vision and Pattern Recognition, CVPR 2025 | H8: IEEE | I8: https://doi.org/10.1109/CVPR52734.2025.02272 | J8: Conference paper | K8: IEEE Xplore | L8: Application-focused | M8: 4.5 | N8: Computer Vision and Image Understanding | O8: Image classification on CIFAR-10, CIFAR-100, and ImageNet-1K | P8: Static RGB image data represented as repeated image sequences over timesteps | Q8: 2D images converted into spiking patch sequences, I ∈ R(T×C×H×W), then represented as N flattened spike patches with D-dimensional channels | R8: CIFAR images are 32 × 32; ImageNet-1K images are resized to 224 × 224; images are repeated across T timesteps; main experiments use 4 timesteps | S8: CIFAR-10, CIFAR-100, ImageNet-1K | T8: Public image classification benchmark datasets | U8: CIFAR: 50,000 training images and 10,000 test images; ImageNet-1K: approximately 1.28 million training images and 50,000 test images | V8: Uses standard train/test benchmark splits; exact class-balance details NR | W8: Spiking Transformer with Spiking Patch Splitting, L-block Spiking Transformer encoder, Accurate Addition-Only Spiking Self-Attention, MLP block, membrane-potential residual connections, global average pooling, and classification head | X8: LIF spike neuron layers, binary spiking neuron for Q, ternary spiking neuron for V, binary spike hidden states, membrane potential dynamics, spike-based residual structure | Y8: LIF; binary spiking neuron; ternary spiking neuron | Z8: Spiking Transformer encoder block, A2OS2A attention module, MLP block, patch-splitting module, relative position embedding, classification head | AA8: Accurate Addition-Only Spiking Self-Attention; binary Q, ReLU/full-precision K, ternary V; softmax-free and scaling-free attention | AB8: Linear + BN layers generate Q, K, and V; Q is converted by binary spiking neuron, K by ReLU, and V by ternary spiking neuron; Q·Kᵀ·V is computed through addition-only operations instead of conventional multiplication-heavy self-attention | AC8: Reported models include Spiking Transformer-2-256, 2-384, 4-256, 4-384, 2-512, 8-384, 6-512, 8-512, and 10-512; main ImageNet models use 4 timesteps | AD8: CIFAR models: 2.59M, 4.15M, 5.76M, 9.32M, and 10.23M depending on model scale; ImageNet models: 16.81M, 23.37M, 29.68M, and 36.01M | AE8: New spiking self-attention mechanism, A2OS2A, designed to reduce information loss while preserving addition-only computation; theoretical analysis of information loss in vanilla spiking self-attention | AF8: Spiking Patch Splitting converts repeated image sequence into spike patch embeddings; spike neuron layer converts membrane potentials into spike tensors | AG8: Main experiments use T = 4 timesteps; binary Q values {0,1}; ternary V values {-1,0,1}; ReLU/full-precision K; LIF threshold Vth, reset potential Vreset, and decay factor β are defined but exact values NR | AH8: Partially learned: patch projection, Q/K/V projections, BN, RPE, and model weights are learned; spike firing rules are fixed neuron dynamics | AI8: Binary spike tensors; binary Q; ternary V; spike patch embeddings; membrane potential tensors; binary hidden states | AJ8: 4 timesteps in the main reported experiments | AK8: Global Average Pooling over final Spiking Transformer encoder output followed by a fully connected classification head | AL8: Yes. The paper provides entropy-based theoretical analysis of information loss in binary spike representations and compares representational capacity of binary spike features versus real-valued features | AM8: Supervised direct learning | AN8: Direct training of Spiking Transformer following Spike-driven Transformer experimental setup; backpropagation with surrogate-gradient-style training implied through LIF neuron discussion | AO8: NR | AP8: N/A | AQ8: NR | AR8: NR | AS8: Main experiments use 4 timesteps; other training configurations follow Spike-driven Transformer; detailed optimizer, learning rate, batch size, and schedule NR | AT8: Top-1 classification accuracy | AU8: Best reported accuracy: 96.42% on CIFAR-10, 79.90% on CIFAR-100, and 78.66% on ImageNet-1K | AV8: Parameter count, timestep count, ablation accuracy gain over baseline | AW8: Hybrid training, Diet-SNN, STBP, STBP-NeuNorm, TSSL-BP, STBP-tdBN, TET, Spikformer, Spikingformer, Spike-driven Transformer, Spiking ResNet, QCFS, COS, SEW-ResNet, Attention-SNN | AX8: CIFAR-10/100: Spiking Transformer-2-512 improves over baseline by about 0.91% on CIFAR-10 and 1.07% on CIFAR-100. ImageNet: Spiking Transformer-8-512 reaches 76.28%, improving over Spikingformer-8-512 by 1.49%; Spiking Transformer-10-512 reaches 78.66% | AY8: Benchmark comparison and ablation study; no standard deviation, confidence interval, repeated-run analysis, or statistical significance test reported | AZ8: Full/clear ablation. Compares baseline Spike-driven Transformer variants against the proposed Spiking Transformer on CIFAR-10 and CIFAR-100 for 2-256 and 2-512 models | BA8: Training framework NR; code availability NR | BB8: Neuromorphic hardware motivation discussed; no specific hardware deployment target used in experiments | BC8: No hardware deployment reported | BD8: No measured energy result; efficiency is argued theoretically through addition-only computation, removal of softmax/scaling, and SNN event-driven properties | BE8: Reports parameter counts and timesteps; no measured latency, memory footprint, or computational complexity table reported | BF8: Partial. Compares against ANN-to-SNN methods and SNN baselines; does not directly evaluate a matched ANN Transformer baseline in experiments | BG8: Contribution: proposes A2OS2A, a more accurate addition-only spiking self-attention mechanism using binary Q, ReLU K, and ternary V to reduce information loss while avoiding softmax and scaling. Limitation: no hardware implementation or measured energy/latency results; several training details are not reported and are referred to prior baseline settings | BH8: Primary: RQ2; Secondary: RQ3, RQ4, RQ1
A9: P008 | B9: Jung, H., Lee, K., & Park, J. (2026). A Structured-Sparsity-Based Design Approach for Energy-Efficient Spiking Transformer Processing. IEEE Transactions on Very Large Scale Integration (VLSI) Systems. https://doi.org/10.1109/TVLSI.2026.3675299 | C9: A Structured-Sparsity-Based Design Approach for Energy-Efficient Spiking Transformer Processing | D9: Korea University | E9: South Korea | F9: 2026 | G9: IEEE Transactions on Very Large Scale Integration (VLSI) Systems | H9: IEEE | I9: https://doi.org/10.1109/TVLSI.2026.3675299 | J9: Journal article | K9: IEEE Xplore | L9: Hardware-focused | M9: 4.5 | N9: Neuromorphic Hardware and Edge AI Acceleration | O9: Structured-sparsity-based acceleration of Spiking Transformer SSA blocks for image classification, object detection, and semantic segmentation | P9: Static image data represented through spike activations in Spiking Transformer models | Q9: Spiking token tensors with timestep, token, and channel dimensions; SSA inputs represented as X ∈ {0,1}^(T×N×Cin), with Q/K/V split into attention heads | R9: Binary spike activations; sparse SSA intermediate matrix A and output matrix Z; rowwise sparsity in A and columnwise sparsity in Z; low-spike-rate neurons firing at most once across timesteps are filtered during sparsity detection | S9: ImageNet-1K, CIFAR-10, CIFAR-100, COCO 2017, ADE20K | T9: Public image classification, object detection, and semantic segmentation benchmark datasets | U9: NR | V9: NR | W9: Spiking Transformer SSA block with QKV generation, SSA/FSSA mechanism, and projection layer; proposed fully spiking SSA inserts additional LIF neuron after KᵀV to increase structured sparsity | X9: LIF neurons, spike activations, FSSA operator, low-spike-rate neuron filtering, sparse spike tensors, structured sparsity detection | Y9: LIF neuron with learnable threshold voltage | Z9: Spiking self-attention block; QKV generation layer; attention heads; projection layer; Spikingformer, Spike-driven Transformer v2, and QKFormer models | AA9: Spiking self-attention; fully spiking SSA; structured-sparsity-aware SSA | AB9: Q, K, and V are generated as spike tensors using spiking neuron layers; FSSA adds LIF neuron to transform intermediate KᵀV attention matrix into sparse spike activation before Q·A computation | AC9: Evaluated ST models include Spikingformer, Spike-driven Transformer v2, QKFormer-224, and QKFormer-384; exact block counts and parameter counts for each model NR in this paper | AD9: Object detection SDT v2: 34.9M; ADE20K semantic segmentation SDT v2: 16.5M; classification model parameter counts NR | AE9: Algorithm–hardware co-design introducing FSSA, low-spike-rate neuron filtering, sparsity-aware two-stage dataflow, and sparsity-aware hardware add-on for runtime computation and memory-transfer skipping | AF9: Uses pretrained Spiking Transformer models with binary spike activations; exact image-to-spike input encoding method NR | AG9: FSSA LIF threshold initialized to vth = 4; neuron filtering treats neurons firing at most once over all timesteps as sparse; fine-tuning for 10 epochs | AH9: Partially learned: FSSA LIF thresholds are learnable and QKV generation weights are fine-tuned; sparsity detection/filtering logic is fixed | AI9: Binary spike activations; spike tensors Q, K, V; sparse A and Z matrices; compact binary sparsity vectors for active/inactive channels | AJ9: T timesteps used in evaluated ST models; exact timestep varies by model/task and is not fully reported; COCO uses timestep 1, ADE20K uses timestep 4 | AK9: Classification head / downstream task heads from the underlying ST models; exact decoding details NR | AL9: Yes. The paper analyzes SSA structured sparsity, rowwise sparsity in A, columnwise sparsity in Z, low-spike-rate neurons across timesteps, and sparsity effects on computation and memory skipping | AM9: Supervised fine-tuning of pretrained Spiking Transformer models | AN9: Lightweight fine-tuning restricted mainly to QKV generation layers and learnable FSSA LIF thresholds; 10 epochs of fine-tuning | AO9: NR | AP9: N/A | AQ9: NR | AR9: NR | AS9: FSSA threshold initialized to 4; fine-tuned for 10 epochs; QKV generation weights updated; up to 80% fewer fine-tuned parameters than full-model fine-tuning; other optimizer and learning-rate details NR | AT9: Effective throughput and energy efficiency of SSA block processing | AU9: Proposed design with filtering achieves 234.44 GOP/s effective throughput and 319.12 GOP/J energy efficiency | AV9: Accuracy, structured sparsity, row-A sparsity, column-Z sparsity, area overhead, power overhead, mAP, mIoU | AW9: Baseline SSA/ST models; Spikingformer, Spike-driven Transformer v2, QKFormer; baseline SNN accelerator/Prosperity; PTB; Bishop; SpikeX; Phi | AX9: FSSA increases structured sparsity by about 1.8× with less than 1% accuracy loss; neuron filtering adds about 1.5× more sparsity over FSSA; proposed hardware achieves 24.3% throughput gain and 28.2% energy-efficiency gain over baseline SNN accelerator | AY9: Benchmark evaluation and postsynthesis simulation; no standard deviation, confidence interval, repeated-run analysis, or statistical significance test reported | AZ9: Full. Includes FSSA direct implementation, FSSA suppression-method comparison, FSSA fine-tuning, neuron-filtering fine-tuning, downstream detection/segmentation evaluation, hardware overhead, and accelerator comparison | BA9: Hardware implemented in Verilog RTL; synthesized with Synopsys Design Compiler in 28 nm process; evaluated using open-source cycle-accurate simulator for Prosperity; training framework/code availability NR | BB9: 28 nm SNN accelerator-style hardware integrated with sparsity-aware hardware modules; baseline modeled using Prosperity accelerator framework | BC9: RTL synthesis and cycle-accurate simulation; no fabricated chip reported | BD9: Energy estimated from postsynthesis simulation and synthesized hardware power; proposed sparsity-aware hardware consumes 2.23 mW with 0.24% power overhead over baseline | BE9: Proposed sparsity-aware hardware area 0.0057 mm²; 1.08% area overhead; 500 MHz frequency; 128 processing elements; skips redundant computations and weight transfers in Q generation and projection layers | BF9: Partial. Motivation compares ST accuracy/efficiency with ANN transformers, but experiments mainly compare against SNN/ST models and SNN accelerators rather than a matched ANN baseline | BG9: Contribution: identifies and exploits structured sparsity in SSA through FSSA, low-spike-rate neuron filtering, and sparsity-aware hardware/dataflow to improve ST throughput and energy efficiency. Limitation: hardware results are based on RTL synthesis and simulation rather than fabricated silicon; optimization focuses mainly on SSA blocks rather than full end-to-end accelerator deployment | BH9: Primary: RQ5; Secondary: RQ2, RQ3, RQ4
A10: P009 | B10: Kim, S., Kim, S., Jo, W., Kim, S., Hong, S., Lee, N., Lee, J., & Yoo, H.-J. (2025). C-Transformer: An Energy-Efficient Homogeneous DNN-Transformer/SNN-Transformer Processor for Large Language Models. IEEE Journal of Solid-State Circuits, 60(10), 3802–3815. https://doi.org/10.1109/JSSC.2025.3554699 | C10: C-Transformer: An Energy-Efficient Homogeneous DNN-Transformer/SNN-Transformer Processor for Large Language Models | D10: Korea Advanced Institute of Science and Technology | E10: South Korea | F10: 2025 | G10: IEEE Journal of Solid-State Circuits | H10: IEEE | I10: https://doi.org/10.1109/JSSC.2025.3554699 | J10: Journal article | K10: IEEE Xplore | L10: Hardware-focused | M10: 4.5 | N10: Neuromorphic Hardware and Edge AI Acceleration | O10: Language modeling, translation, and summarization using GPT-2, mT5, T5, and FSMT | P10: Text/token sequence data; spike trains used internally for SNN-Transformer mode | Q10: 1D language token sequences; encoding uses 1024 input tokens and decoding generates one output token in the measurement setup | R10: Tokenized language input processed by Transformer models; INT8 activations/weights in HDSC; rate-coded spike trains in spiking-Transformer mode; outlier inputs handled by INT16 1-D SIMD | S10: WikiText, IWSLT, CNN/DailyMail; FSMT translation dataset NR | T10: Public NLP benchmark datasets for language modeling, translation, and summarization | U10: NR | V10: NR | W10: Homogeneous DNN-Transformer/SNN-Transformer processor using complementary DNN-style allocation; workload dynamically switches between DNN-Transformer mode and spiking-Transformer mode based on input magnitude | X10: Spiking-Transformer mode, rate encoding, spike trains, integrate-and-fire operations, output spike speculation, spike-level zero skipping | Y10: Integrate-and-fire style spike generation; exact neuron model beyond threshold-based integrate-and-fire NR | Z10: DNN-Transformer and spiking-Transformer execution for GPT-2, mT5, T5, and FSMT language models; attention and feed-forward blocks processed in HDSC | AA10: Transformer self-attention / multi-self-masked attention; spiking-Transformer computations use spike-domain operations; exact SNN attention formulation NR | AB10: Input loader converts scalar input values into spike trains in ST-mode; HMAU reconfigures between MAC operation for DNN-Transformer mode and accumulation operation for spiking-Transformer mode; workload allocator selects efficient network type based on input magnitude | AC10: GPT-2 Large: 708M parameters, 36 blocks; GPT-2 Small: 12 blocks; mT5 Large: 24 blocks; mT5 Small: 8 blocks; T5 Large: 24 blocks; T5 Small: 6 blocks | AD10: GPT-2 Large: 708M; T5 Large: 402M; other model parameter counts partly NR | AE10: Fabricated ASIC processor with homogeneous DNN/SNN Transformer core, hybrid multiplication/accumulation unit, output spike speculation, spike-level zero skipping, big–little network compression, implicit weight generation, and extended sign compression | AF10: Rate encoding converts input values into spike trains in spiking-Transformer mode | AG10: INT8 input/weight precision in HDSC; INT16 outlier handling; threshold set to match DNN LSB resolution; time window configured as 2^(w−1); output spike speculation sampling ratios selected from {0, 25, 50, 75} | AH10: Fixed rate-encoding and hardware-level spike speculation; model parameters/compression components are trained or generated separately | AI10: Rate-coded spike train; 1-bit spike activity; sampled output spike probability; speculated output spike patterns for remaining timesteps | AJ10: Time-window-based spike processing; exact total timestep depends on word length and fixed-point configuration; layer-wise sampling ratios include 25%, 50%, and 75% | AK10: Transformer language-model decoding generates output tokens; output spike speculation estimates full-time-step spike patterns from sampled timesteps | AL10: Partial. The paper analyzes rate-coding spike probability, sampled timestep behavior, output spike speculation, and layer-wise sampling ratios, but does not deeply analyze temporal information preservation | AM10: Hardware inference paper; uses pretrained/compressed language models | AN10: Big–little network and implicit weight generation are adopted for compression; exact LLM training/fine-tuning procedure NR | AO10: NR | AP10: NR | AQ10: NR | AR10: For implicit weight generation, losses are calculated from differences between parameters, feature maps, and logits; exact formulas NR | AS10: NR | AT10: System energy consumption, computation energy, EMA energy, latency, energy efficiency | AU10: GPT-2 language modeling: 35.9 mJ and 656 ms; mT5 translation: 21.3 mJ and 359 ms; T5 summarization: 15.0 mJ and 307 ms; FSMT translation: 5.5 mJ and 93 ms | AV10: Perplexity, BLEU, ROUGE-L, TOPS/W, TOPS, external bandwidth, memory-access reduction, compression ratio, throughput | AW10: Baseline without proposed features; previous Transformer ASICs from ISSCC 2022/2023; C-DNN processor; DDR3 EMA baseline | AX10: Achieves 0.21×–0.33× computation energy and 0.31×–0.41× EMA energy compared with baseline; HDSC gives 1.32× chip energy-efficiency gain, spike-level zero skipping 1.21×, and output spike speculation 1.19×; total system energy reduced to 0.43× | AY10: Chip measurement and benchmark comparison; no standard deviation, confidence interval, repeated-run analysis, or statistical significance test reported | AZ10: Full hardware feature analysis. Includes HDSC, spike-level zero skipping, output spike speculation, BLN, IWG, ESC, layer-wise energy/latency, compression performance, and sampling-ratio analysis | BA10: Fabricated Samsung 28-nm 1P8M CMOS ASIC; evaluation board with DDR3 DRAM, flash memory, FPGA, and host PC; code availability NR | BB10: Fabricated 28-nm Samsung 1P8M CMOS ASIC with 48 homogeneous DNN/SNN Transformer cores, two weight generators, NoC, top controller, 1-D SIMD unit, and 500 KB SRAM | BC10: Fabricated and measured silicon chip with demonstration system | BD10: Measured chip/system energy; includes EMA energy estimation using DDR3 interface; chip consumes 47.5 mW at 50 MHz/0.7 V and 469.2 mW at 200 MHz/1.1 V | BE10: Die area 20.25 mm²; 0.7–1.1 V; 50–200 MHz; peak performance 3.41 TOPS; energy efficiency 22.9–47.8 TOPS/W; 1.6 GB/s external bandwidth; 500 KB SRAM | BF10: Yes. Compares against DNN-Transformer processing, previous non-spiking Transformer ASICs, and baseline Transformer execution with EMA energy | BG10: Contribution: proposes and fabricates C-Transformer, a homogeneous DNN-Transformer/SNN-Transformer ASIC for on-device language models using reconfigurable HMAU, output spike speculation, and three-stage weight compression to reduce computation and external-memory energy. Limitation: spiking mechanism is mainly hardware-level rate-coded processing rather than a fully reported SNN training method; some training and dataset details are NR | BH10: Primary: RQ5; Secondary: RQ2, RQ3
A11: P010 | B11: Leone, G., Busia, P., Orrù, M., Raffo, L., & Meloni, P. (2025). ESTU: Enabling Spiking Transformers on Ultra-Low-Power FPGAs. IEEE Transactions on Circuits and Systems II: Express Briefs, 72(12), 2027–2031. https://doi.org/10.1109/TCSII.2025.3626209 | C11: ESTU: Enabling Spiking Transformers on Ultra-Low-Power FPGAs | D11: University of Cagliari | E11: Italy | F11: 2025 | G11: IEEE Transactions on Circuits and Systems II: Express Briefs | H11: IEEE | I11: https://doi.org/10.1109/TCSII.2025.3626209 | J11: Journal article | K11: IEEE Xplore | L11: Hardware-focused | M11: 4 | N11: Biomedical and Healthcare Signal Processing | O11: Spiking Transformer inference on low-power FPGA; sEMG gesture classification on NinaPro DB-5; benchmarking of spiking Transformer models for fast prosthetic hand control and epileptic seizure detection/prediction | P11: Sensor time-series converted into spike trains; sEMG signals; EEG/seizure-related benchmark model; generic spike-token inputs | Q11: Temporal sensor streams represented as spike sequences; model uses token/patch sequence length, attention heads, embedding dimensions, and timesteps | R11: sEMG data are converted into spikes using delta modulation; sEMG model uses 32 input channels, embedding size 64, 4 attention heads, 200 timestep memory for K and V, and projection size 16; 91% neurons inactive on average during test inference | S11: NinaPro DB-5; benchmark models from prior fast prosthetic hand control and epileptic seizure detection/prediction studies | T11: Public biomedical sensor dataset and prior benchmark spiking Transformer models | U11: NR | V11: NR | W11: Microcode-programmable Spiking Transformer accelerator with configurable encoding slot, ESTU accelerator core, configurable decoding slot, and RISC-V softcore; supports embedding, encoder/SSA, and classifier stages | X11: LIF neuron module, spike trains, spike memory, spike-weight and spike-spike operations, sparsity stack memory, event-sparsity exploitation | Y11: LIF | Z11: Spiking Transformer encoder; lightweight spiking self-attention; Q/K/V projections; multi-head attention; classifier stage | AA11: Spiking self-attention; softmax-free attention using binary Q, K, and V projections | AB11: Sensor data are converted into spike trains by a configurable encoding slot; ESTU executes dense, sum, and matrix multiplication operators over spike/integer data; operation results can be passed through LIF to generate binary spike outputs for subsequent Transformer layers | AC11: sEMG model: dense-based embedding plus one encoder stage, 4 attention heads, K/V memory of 200 timesteps, projection size 16, 32 input channels, embedding size 64. Benchmarked models include configurations with 8 heads/32 patch/150 sequence length and 1 head/8 patch/24 sequence length | AD11: NR | AE11: Ultra-low-power FPGA architecture named ESTU; microcode-programmable accelerator; operator fusion and hardware reuse; sparsity-aware execution; RISC-V-controlled system; configurable encoding/decoding slots | AF11: Delta modulation for sEMG spike feature extraction; configurable encoding slot for sensor-to-spike conversion | AG11: sEMG model uses 32 input channels; K/V memory length 200 timesteps; embedding size 64; projection size 16; 8-bit integer quantized model parameters; 20-bit fixed-point membrane potentials | AH11: Fixed/preprocessing-based encoding; model weights trained separately; ESTU hardware/microcode is configurable | AI11: Spike trains; grouped spikes in blocks of four for stack-memory sparsity tracking; binary spike memory; LIF-generated spikes | AJ11: sEMG model uses 200 timestep memory for K and V; other benchmark models use sequence lengths of 150 and 24; exact sampling rate NR | AK11: Configurable decoding slot; spike-rate evaluation mentioned as an example for classification outcome generation | AL11: Partial. The paper analyzes spike grouping, event sparsity exploitation, inactive-neuron rate, and real-time constraints, but does not deeply analyze temporal information preservation | AM11: Supervised training for sEMG Spiking Transformer model; hardware inference deployment | AN11: SpikingJelly used to train the sEMG Spiking Transformer; post-training uniform-scale quantization applied for deployment | AO11: NR | AP11: N/A | AQ11: NR | AR11: NR | AS11: 8-bit integer post-training quantization for parameters; 20-bit fixed-point membrane potentials; other training hyperparameters NR | AT11: Inference power consumption and real-time execution capability | AU11: Active inference power: 3.76 mW; standby power: 0.23 mW; sEMG classification accuracy: 87.21% before quantization and 86.97% after quantization | AV11: Execution time, energy per inference, throughput per operator, sparsity, resource utilization, accuracy improvement, standby power | AW11: Vanilla SNN model for sEMG classification; RISC-V microcontroller baseline; FPGA-based spiking Transformer accelerators from prior work | AX11: sEMG Spiking Transformer improves accuracy by over 2% compared with vanilla SNN; 91% inactive neurons provide 29% speedup compared with non-sparse execution; energy efficiency is reported as 2.6× higher than one prior work and 2× higher than another FPGA spiking Transformer accelerator | AY11: Benchmark and hardware measurements reported; no standard deviation, confidence interval, repeated-run analysis, or statistical significance test reported | AZ11: Partial. Includes sparsity grouping trade-off, operator throughput comparison, benchmark model execution, quantization impact, sparsity speedup, and power measurement | BA11: SpikingJelly for model training; ESTU is stated as open-source; hardware synthesized with OSS CAD Suite, Yosys, and nextpnr; GitHub repository provided in the paper | BB11: Lattice iCE40UP5K ultra-low-power FPGA with RISC-V SERV softcore | BC11: Implemented and measured on FPGA evaluation board | BD11: Measured using shunt resistor on the VCORE track of the iCEBreaker evaluation board; active power 3.76 mW, standby 0.23 mW; at 12 MHz, average power 1.03 mW and 4.28 µJ per inference for sEMG | BE11: Maximum clock 21 MHz; resource usage: 4,301 logic cells, 30 BRAMs, 2 SPRAMs, 6 DSPs; memory limits: <1 Mb integer memory for attention/synaptic weights, 32 Kb spike memory, 768 LIF neurons; sEMG inference about 0.65 ms with 91% sparsity | BF11: No direct ANN baseline; compares mainly with vanilla SNN, RISC-V software execution, and FPGA spiking Transformer accelerators | BG11: Contribution: proposes ESTU, an ultra-low-power, microcode-programmable Spiking Transformer FPGA architecture for near-sensor edge inference, validated on sEMG and benchmark models with measured milliwatt-level power. Limitation: limited model size due to small FPGA memory; low peak performance compared with high-end FPGA accelerators; training details are not fully reported | BH11: Primary: RQ5; Secondary: RQ1, RQ2, RQ3
A12: P011 | B12: Li, T., Li, J., Shen, G., Zhao, D., Zhang, Q., & Zeng, Y. (2026). FireFly-T: High-Throughput Sparsity Exploitation for Spiking Transformer Acceleration with Dual-Engine Overlay Architecture. IEEE Transactions on Computers. https://doi.org/10.1109/TC.2026.3672901 | C12: FireFly-T: High-Throughput Sparsity Exploitation for Spiking Transformer Acceleration with Dual-Engine Overlay Architecture | D12: University of Chinese Academy of Sciences | E12: China | F12: 2026 | G12: IEEE Transactions on Computers | H12: IEEE | I12: https://doi.org/10.1109/TC.2026.3672901 | J12: Journal article | K12: IEEE Xplore | L12: Hardware-focused | M12: 4.5 | N12: Neuromorphic Hardware and Edge AI Acceleration | O12: FPGA acceleration of spiking convolutional networks and Spiking Transformer inference, especially sparse activation processing and spiking attention acceleration | P12: Static image data converted into spike-based feature/token representations | Q12: 2D image input represented as spike feature maps and spiking token sequences | R12: Uses 1-bit spike activations, sparse spike feature maps, binary Q/K/V attention operands, and multi-bit weights; CIFAR-Net input begins from 3 × 32 × 32 images | S12: CIFAR-10, CIFAR-100, ImageNet | T12: Public image classification benchmark datasets | U12: NR | V12: NR | W12: Spiking Transformer mapped onto a dual-engine FPGA overlay; model side follows SPS + stacked Spiking Transformer encoder blocks + classification head; hardware side uses sparse engine for convolution/linear layers and binary engine for spiking attention | X12: LIF neurons, spiking patch splitting, spiking convolution, sparse spike activations, neuronal dynamics module, spike-based MLP, spike-form Q/K/V | Y12: LIF | Z12: Spiking Transformer encoder, Spiking Self-Attention, MLP block, Spikingformer variants, classification head | AA12: Binary spiking self-attention; spiking attention using AND-PopCount operations | AB12: Spike-form Q, K, and V are processed by the binary engine; sparse engine handles spiking convolution/linear operations, while binary engine accelerates QKᵀ and QKᵀV attention operations through LUT6-optimized AND-PopCount logic | AC12: Evaluated models include CIFAR-Net, Spikingformer-4-256 for CIFAR-10, Spikingformer-2-512 for CIFAR-100, and Spikingformer-8-512 for ImageNet; hardware parallelism configured as (PTs × PFx, PCi, PCo) = (8 × 16, 64) | AD12: NR | AE12: Dual-engine overlay architecture; high-throughput sparse engine; binary spiking-attention engine; flexible orchestrator; multi-lane sparse decoder; bank-conflict-free workload balancing; LUT6-optimized AND-PopCount; implicit transpose/dataflow manipulation | AF12: Spiking Patch Splitting / spiking convolutional tokenizer; exact raw image-to-spike encoding rule NR | AG12: 1-bit spike activations; binary attention operands; configurable timestep, sequence length, embedding dimension, kernel size, channel parallelism, memory banks, and sparse decoder throughput; exact neuron threshold values NR | AH12: Partially model-based and hardware-configurable; exact encoding learning status NR | AI12: Binary spike feature maps; sparse spike bitmap/index representations; spike-form Q/K/V; fine-grained sparse activations | AJ12: Symbolic timestep parameter Ts supported by the architecture; exact timestep used in each evaluated network NR | AK12: Classification head produces final image classification output | AL12: Yes. The paper analyzes spike sparsity, fine-grained versus coarse-grained sparsity, multidimensional parallelism, sparse decoder throughput, binary attention dataflow, and resource/energy trade-offs | AM12: Hardware inference acceleration; model training is not the main focus | AN12: NR | AO12: NR | AP12: N/A | AQ12: NR | AR12: NR | AS12: NR | AT12: Energy efficiency, throughput, DSP efficiency, and classification accuracy | AU12: FireFly-T reports 978.61 GOP/s/W on CIFAR-Net/CIFAR-10; Spikingformer results include 696.64 GOP/s/W on CIFAR-10, 762.87 GOP/s/W on CIFAR-100, and 781.13 GOP/s/W on ImageNet; reported accuracies include 93.60%, 94.45%, 78.38%, and 71.55% across the evaluated configurations | AV12: GOP/s, GOP/s/DSP, FPS, LUT usage, register usage, BRAM usage, DSP usage, clock frequency, resource breakdown | AW12: E3NE, SyncNN, DeepFire2, FireFly v2, HeatViT, SSR, SpikeTA, and other SNN / Transformer accelerators | AX12: Achieves 1.39× higher energy efficiency and 4.21× higher DSP efficiency than FireFly v2; achieves 2.40× higher energy efficiency and 7.10× higher DSP efficiency than SpikeTA; also reports 1.47×–13.87× higher energy efficiency than DeepFire2 and 1.03×–1.39× higher than FireFly v2 across CIFAR-10, CIFAR-100, and ImageNet | AY12: Hardware benchmark comparison and resource/performance evaluation; no standard deviation, confidence interval, repeated-run analysis, or statistical significance test reported | AZ12: Full hardware analysis. Includes sparsity support comparison, sparse decoder analysis, load-balancing analysis, parallelism/sparsity comparison, resource breakdown, and comparison with SOTA accelerators | BA12: FPGA implementation on Zynq UltraScale+ MPSoC / KV260 platform; code availability NR | BB12: Xilinx Zynq UltraScale+ MPSoC / KV260 FPGA platform; xczu5ev device | BC12: Implemented and evaluated as an FPGA overlay/IP accelerator on commercial FPGA edge hardware | BD12: Energy efficiency and power/resource metrics are reported from FPGA implementation/Vivado-style evaluation; no fabricated ASIC measurement | BE12: FireFly-T uses 46 kLUTs, 117 kREGs, 100 BRAMs, and 304 DSPs at 300 MHz for the G=4 configuration; sparse engine uses 40 kLUTs and 288 DSPs, while binary engine uses 5 kLUTs and 16 DSPs | BF12: Partial. The paper compares against non-spiking Transformer accelerators such as HeatViT and SSR, but it does not provide a matched ANN Transformer model comparison under the same task/model setting | BG12: Contribution: FireFly-T is a practical FPGA accelerator for Spiking Transformers that combines fine-grained sparsity exploitation, multidimensional parallelism, and a dedicated binary attention engine. Limitation: evaluation is FPGA-based rather than fabricated ASIC; experiments focus mainly on image-classification workloads; training and encoding details are not deeply reported | BH12: Primary: RQ5; Secondary: RQ2, RQ3
A13: P012 | B13: Liu, Z., Wu, J., Shi, G., Yang, W., Dong, W., & Zhao, Q. (2024). Motion-Oriented Hybrid Spiking Neural Networks for Event-Based Motion Deblurring. IEEE Transactions on Circuits and Systems for Video Technology, 34(5), 3742–3754. https://doi.org/10.1109/TCSVT.2023.3317976 | C13: Motion-Oriented Hybrid Spiking Neural Networks for Event-Based Motion Deblurring | D13: University, Xi’an | E13: China | F13: 2024 | G13: IEEE Transactions on Circuits and Systems for Video Technology | H13: IEEE | I13: https://doi.org/10.1109/TCSVT.2023.3317976 | J13: Journal article | K13: IEEE Xplore | L13: Application-focused | M13: 4.5 | N13: Event-Based / Neuromorphic Vision | O13: Event-based motion deblurring / sharp image reconstruction from blurry image and event stream | P13: Blurry RGB/image frames and event-camera data | Q13: Multimodal 2D image + 3D spatiotemporal event/spike representation | R13: Event stream represented as asynchronous events (x, y, t, p); event cameras provide microsecond-level temporal resolution; spike features are represented in spatiotemporal form S ∈ R^(n×n×T×C); GoPro images are 1280 × 720; real-event images are cropped to 320 × 256 | S13: GoPro, REBlur, and a custom real-event dataset captured using DAVIS346 | T13: Mixed: public synthetic event-based deblurring dataset, public real-event deblurring dataset, and custom real-event dataset | U13: GoPro: 3,214 image pairs, with 1,111 test samples; REBlur: 1,389 pairs, with 486 training and 903 testing pairs; custom real-event dataset: 6,309 pairs, with 2,075 test samples | V13: GoPro and custom real-event datasets use about one-third of samples for testing; REBlur uses 486 train / 903 test pairs; class balance N/A | W13: Hybrid SNN-CNN two-stream deblurring network; SNN branch extracts motion features from events, CNN branch extracts background/image features, TSST computes spike motion intensity, and HFEE fuses SNN motion features with CNN features for reconstruction | X13: SNN event feature extractor, spiking convolution, spiking pooling, LIF neurons, Temporal-local-Spatio Spiking Transformer, spike temporal attention | Y13: LIF | Z13: Temporal-local-Spatio Spiking Transformer; spiking temporal attention map; attention over local spatial windows and temporal spike sequences | AA13: Spiking temporal attention; temporal-local-spatio self-attention; channel attention in the CNN fusion block | AB13: SNN extracts spike features from events; TSST computes motion intensity maps from local spike release rates and temporal attention; spike features are scaled by the motion-attention map and converted/mapped into floating-point features for CNN fusion through HFEE | AC13: Deblurring network uses 4-layer encoder and 4-layer decoder; CNN encoder feature dimensions are [32, 64, 128, 256]; SNN branch dimensions are [8, 16, 32, 64]; SNN experiments use 10 temporal sequences; TSST window sizes tested from 16 to 128, with best reported setting around 32 | AD13: Full model on real-event dataset: 7.11M parameters; TSST SNN branch parameters reported as 40.938 KB in ablation | AE13: New event-based motion deblurring architecture; first use of SNN-CNN hybrid fusion for image deblurring; proposed TSST for motion intensity extraction; proposed HFEE for motion-background feature fusion | AF13: Event-to-spike temporal sequence encoding; raw event temporal sequence is compressed into 10 spike timesteps; event spikes are sampled to millisecond scale for GoPro; blurry image is processed by CNN branch | AG13: LIF threshold Vth = 1; leak factor τ = 0.5; initial membrane potential u(0)=0; SNN temporal sequence length Tout = 10; TSST spatial window sizes [32, 16, 8, 4] across encoder layers; GoPro events are temporally extended by doubling timestamps | AH13: Partially fixed and learned: event-to-spike temporal binning and LIF dynamics are fixed; SNN/CNN feature extraction and fusion weights are learned end-to-end | AI13: Binary spike sequences; sparse event stream; spatiotemporal spike tensor; spike motion intensity map; mapped floating-point motion feature after TSST | AJ13: Event camera has microsecond-level event triggering; model training uses 10 SNN temporal sequences; GoPro maximum timestamp around 40,000; custom real-event maximum timestamp around 300,000 | AK13: CNN decoder reconstructs the final sharp RGB image from fused SNN-CNN features | AL13: Yes. The paper analyzes motion intensity from spike density and temporal attention, TSST window-size effects, spike-to-CNN feature fusion, and the importance of preserving temporal motion information during deblurring | AM13: Supervised end-to-end image reconstruction | AN13: Joint SNN-CNN optimization using backpropagation through time for SNN modules and surrogate-gradient training for spike non-differentiability | AO13: Triangle surrogate gradient function | AP13: N/A | AQ13: Adam | AR13: Charbonnier loss plus edge loss: L = Lchar(Z, GT) + λLedge(Z, GT) | AS13: GoPro: random 512 × 512 crops, batch size 16, Adam, learning rate decreases from 3 × 10⁻⁴ to 1 × 10⁻⁶. Real Events: GoPro pretrained model initialization except SNN neurons, Adam, learning rate decreases from 1 × 10⁻⁴ to 1 × 10⁻⁵, batch size 16. Loss weight λ = 0.05, ε = 1 × 10⁻³ | AT13: PSNR and SSIM | AU13: GoPro: 35.58 dB PSNR; Real Event dataset: 34.67 dB PSNR and 0.968 SSIM; REBlur: 40.15 dB PSNR | AV13: Parameter count, ablation PSNR/SSIM, visual deblurring quality, comparison with image-only and event-based baselines | AW13: DMPHN, MPRNet, MIMO-UNet++, Restormer, D2Nets, NAFNet, DS-Deblur, ERDNet, eSL-Net, EFNet, Concatenate baseline, SNN TATT, SNN SATT, LSTM-event baseline | AX13: On GoPro, improves over EFNet by 0.12 dB PSNR and over NAFNet by 1.89 dB. On the custom real-event dataset, improves over EFNet and other SNN-based variants. On REBlur, achieves 40.15 dB PSNR, improving over EFNet by 2.03 dB | AY13: Benchmark comparison and extensive ablation studies; no standard deviation, confidence interval, repeated-run analysis, or statistical significance test reported | AZ13: Full. Includes event pathway removal, LSTM event baseline, TSST vs Concatenate/SNN TATT/SNN SATT, TSST window-size analysis, parameterized vs non-parameterized fusion block, and Charbonnier/edge-loss ablation | BA13: PyTorch; trained using two Intel Xeon Gold 6226R CPUs and four NVIDIA RTX 3090 GPUs; code and pretrained models available at GitHub: XDULzx/MotionSNN | BB13: No direct deployment; neuromorphic chip potential discussed for future work | BC13: No real neuromorphic hardware deployment reported | BD13: No direct energy measurement; paper motivates SNN efficiency and notes that full SNN benefits require brain-like/neuromorphic chip deployment | BE13: Reports parameter counts and model size in ablations; no measured latency, memory footprint, FLOPs, or hardware energy table reported | BF13: Yes. Compares with CNN/Transformer/image-restoration baselines such as Restormer, NAFNet, MPRNet, MIMO-UNet++, and event-based ANN deblurring methods | BG13: Contribution: proposes TSST and HFEE to fuse event-based SNN motion features with CNN background features for motion deblurring, showing strong PSNR/SSIM on GoPro, REBlur, and real-event data. Limitation: low-power and high-temporal-resolution advantages of SNNs are not fully demonstrated because no neuromorphic chip deployment or energy measurement is provided | BH13: Primary: RQ1; Secondary: RQ2, RQ3, RQ4, RQ5
... A119: P118 | B119: Cao, H., Zhou, Z., Wei, W., Liang, Y., Belatreche, A., Zhang, D., Zhang, M., Yang, Y., & Li, H. (2025). Binary Event-Driven Spiking Transformer. In Proceedings of the Thirty-Fourth International Joint Conference on Artificial Intelligence (IJCAI-25), pp. 4110–4118. | C119: Binary Event-Driven Spiking Transformer | D119: University of Electronic Science and Technology of China | E119: China | F119: 2025 | G119: Proceedings of the Thirty-Fourth International Joint Conference on Artificial Intelligence, IJCAI-25 | H119: IJCAI | I119: https://www.ijcai.org/proceedings/2025/0458.pdf | J119: Conference paper | K119: WoS | L119: Efficiency-focused | M119: 4.5 | N119: Neuromorphic Hardware and Edge AI Acceleration | O119: Static image classification and neuromorphic event-based image classification using a binary Spiking Transformer | P119: Static RGB images and neuromorphic/event-camera data | Q119: 2D image data and 2D spatiotemporal event-stream data represented as spike/token sequences | R119: Static images and event streams are processed using binary spike activities; weights and attention maps are binarized to 1-bit; CIFAR10-DVS uses event-stream data; ImageNet uses large-scale static image data | S119: CIFAR-10, CIFAR-100, ImageNet-1K, CIFAR10-DVS | T119: Public static image classification and neuromorphic/event-based vision benchmark datasets | U119: CIFAR-10 and CIFAR-100 standard datasets used; ImageNet-1K used; CIFAR10-DVS used. Exact sample counts NR in the paper | V119: Standard benchmark splits implied; exact train/test split and class-balance details NR | W119: BESTformer combines binary Spiking Patch Splitting, Binary Spiking Self-Attention, Binary Spiking Transformer Encoder Blocks, reversible encoder connections, classification head, and distillation head | X119: LIF neurons, hard-reset LIF, soft-reset LIF, binary spike activities, binary weights, binary attention maps, Binary Spiking Patch Splitting, Binary Spiking Self-Attention | Y119: LIF; HR-LIF for standard spiking dynamics; SR-LIF for attention-map binarization | Z119: BESTformer; Spikformer-style Transformer-based SNN; Binary Spiking Self-Attention; Binary Spiking Encoder Blocks; reversible Transformer encoder | AA119: Binary Spiking Self-Attention; event-driven self-attention; 1-bit binarized attention map | AB119: Binary spike activities are processed through binary convolution and batch normalization; Query and Key generate the attention map Attn = QKᵀ; the attention map is binarized using SR-LIF and then used in Binary Spiking Self-Attention | AC119: BESTformer-2-384, BESTformer-4-384, BESTformer-6-384, BESTformer-8-512, and BESTformer-2-256 are evaluated; ImageNet uses BESTformer-8-512; CIFAR10-DVS uses BESTformer-2-256 | AD119: Parameter count NR; model size reported: BESTformer-2-384 0.73–0.86 MB; BESTformer-4-384 1.18–1.31 MB; BESTformer-8-512 5.57 MB; BESTformer-2-256 0.34 MB | AE119: Binary Event-Driven Spiking Transformer; 1-bit weight binarization; 1-bit attention-map binarization; Coupled Information Enhancement; reversible framework; information-enhancement distillation | AF119: Static images/event inputs are processed through Binary Spiking Patch Splitting and spike-based Transformer blocks; 1-bit spike activities serve as inputs to binary convolution and B-SSA operations | AG119: Weights are binarized to {-1, +1}; spike activities are 1-bit; attention maps are binarized by SR-LIF; Table 1 example uses N = 1, T = 4, threshold Vth = 1, and time constant τ = 0.5. Main experiments use time steps 1, 2, 4, 10, or 16 depending on dataset/model | AH119: Partially learned: model weights, layer-wise attention binarization factors λ, classifier, and distillation heads are learned; binary spike rules and binarization functions are fixed mechanisms | AI119: 1-bit binary spike activities, 1-bit binary weights, binarized attention maps, membrane potentials, spike-form Q/K/V features | AJ119: CIFAR-10/100: mainly 2 or 4 time steps; ImageNet: 1 or 4 time steps; CIFAR10-DVS: 10 or 16 time steps | AK119: Dual-head output: classification head predicts ground-truth class, while distillation head learns from the full-precision teacher model’s hard decision | AL119: Yes. The paper analyzes limited representation capability caused by binarization, value-set size of feature maps, entropy preservation through reversible connections, and attention-map binarization using SR-LIF | AM119: Supervised direct SNN training with knowledge distillation from a full-precision teacher | AN119: Direct training of binary Spiking Transformer with Coupled Information Enhancement, reversible encoder framework, and information-enhancement distillation | AO119: NR | AP119: N/A | AQ119: NR | AR119: Global loss: average of cross-entropy loss for classification head and cross-entropy loss for distillation head using the teacher model’s hard decision | AS119: Detailed implementation settings are stated to be in supplementary materials; optimizer, learning rate, batch size, and epoch count NR in main paper | AT119: Classification accuracy, model size, SOPs, and NS-ACE | AU119: CIFAR-10: BESTformer-4-384 achieves 95.73% with 1-bit weights, 4 timesteps, and 1.18 MB. CIFAR-100: BESTformer-4-384 achieves 79.80% with 1-bit weights, 4 timesteps, and 1.31 MB. ImageNet: BESTformer-8-512 achieves 63.46% with 1-bit weights and 4 timesteps; 62.39% with 1 timestep. CIFAR10-DVS: BESTformer-2-256 achieves 80.80% with 16 timesteps | AV119: Weight bits, time steps, model size, NS-ACE, SOPs, information representation capability, ablation accuracy gain | AW119: CBP-QSNN / Yoo and Jeong, BitSNNs / Hu et al., Quantized Spikformer / Shen et al., SEW-ResNet18, SEW-ResNet34, Spikformer-4-384, Spikformer-8-512, Wide-7B-Net, full-precision Spikingformer | AX119: On ImageNet with 1 timestep, BESTformer-8-512 reaches 62.39%, improving by 7.85% over 1-bit Quantized Spikformer-8-512 at 54.54%. On CIFAR-100, BESTformer-4-384 reaches 79.80%, improving over 2-bit Quantized Spikformer-4-384 at 75.91%. On CIFAR10-DVS, BESTformer-2-256 improves over 1-bit Spikformer-2-256 from 79.80% to 80.80% | AY119: Benchmark comparison and ablation study reported; no standard deviation, confidence interval, repeated-run statistics, or formal statistical significance test reported | AZ119: Full. Includes reversible framework, information-enhancement distillation, dual-head configuration, CIE effects across BESTformer-2-384/4-384/6-384, and information-representation analysis across encoder depth | BA119: Code available at GitHub: CaoHLin/BESTFormer; exact training framework NR | BB119: Resource-constrained edge devices and neuromorphic computing environments; neuromorphic hardware motivation includes TrueNorth, Loihi, and Tianjic | BC119: No real neuromorphic hardware deployment reported | BD119: No measured chip/FPGA energy; efficiency is evaluated using model size, SOPs, and NS-ACE. ImageNet BESTformer-8-512 reports 5.57 MB model size, 2.13G SOPs, and 2.13G NS-ACE | BE119: BESTformer-8-512 on ImageNet reduces model size from full-precision 59.36 MB to 5.57 MB and NS-ACE from 104.32G to 2.13G; direct measured latency and memory footprint beyond model size NR | BF119: Partial. Compares against full-precision Transformer-based SNN counterpart and quantized SNN baselines; no direct matched ANN Transformer baseline in the main tables | BG119: Contribution: proposes BESTformer, a 1-bit binary event-driven Spiking Transformer that binarizes both weights and attention maps, and introduces CIE to recover information lost from binarization through reversible modeling and distillation. Limitation: energy/efficiency evidence is metric-based rather than measured on physical hardware; training details are mostly in supplementary materials; experiments focus on classification tasks | BH119: Primary: RQ2 and RQ5; Secondary: RQ3, RQ4, RQ1

Sheet Eligible (Safuwan)
A1: Title | B1: Application | C1: Year | D1: Conference /Journal | E1: Clarity of Objectives & Scope | F1: Score 1 | G1: Methodological Rigor & Reproducibility | H1: Score 2 | I1: Empirical Validation & Benchmarking | J1: Score 3 | K1: Specification of Encoding & Learning Mechanisms | L1: Score 4 | M1: Acknowledgment of Limitations & Open Challenges | N1: Score 5 | O1: Overall Score | P1: SNN-Transformer Core | Q1: Average Score Reeyan and Safuwan
A2: Optimizing Spiking Neural Networks with Transformer-Based Spatial Attention | B2: Image classification using SNN–Transformer integration | C2: 2024 | D2: 2024 4th International Symposium on Computer Technology and Information Science, ISCTIS, IEEE | E2: The objective is clear. The paper proposes SpikeNetTransformer and TSSA to improve SNN performance using Transformer attention. | F2: 1 | G2: The method has architecture figures, LIF equations, TSSA equations, optimizer, learning rate, batch size, and time step. However, full layer details, code, and complete reproducibility details are missing. | H2: 0.5 | I2: The paper uses CIFAR-10 and CIFAR-100. It compares with several SNN and ANN baselines. It also reports accuracy, parameters, SOPs, energy, and ablation results. | J2: 1 | K2: The paper explains LIF neurons, TSSA, spike-based attention, and scaling factor. However, the exact image-to-spike encoding and learning mechanism are not fully detailed. | L2: 0.5 | M2: The paper gives a short future direction about testing on complex datasets and real-world scenarios. However, limitations are not deeply discussed. | N2: 0.5 | O2: =F2+H2+J2+L2+N2 -> 3.5 | P2: Include > Borderline | Q2: =('Eligible (Safuwan)'!O2+'Eligible (Reeyan)'!O2)/2 -> 3.5
A3: Advanced SpikingYOLOX: Extending Spiking Neural Network on Object Detection with Spike-based Partial Self-Attention and 2D-Spiking Transformer | B3: Object detection using SNN–Transformer integration | C3: 2025 | D3: ACM Multimedia 2025, MM ’25 | E3: The objective is clear. The paper aims to improve SNN-based object detection using PSA-SNN and a 2D-Spiking Transformer. | F3: 1 | G3: The method is well described. It includes architecture figures, equations, training details, loss functions, augmentation, and framework details. However, full hyperparameter values and public code link are not clearly provided. | H3: 0.5 | I3: The validation is strong. It uses COCO2017, reports mAP and AP metrics, compares with ANN, ANN2SNN, and directly trained SNN baselines, and includes ablation studies. | J3: 1 | K3: The encoding and learning mechanisms are clearly explained. The paper uses single-timestep SNN input, LIF-based spike processing, direct end-to-end training, PSA-SNN, and 2D spike-driven self-attention. | L3: 1 | M3: Limitations are only partly discussed. The paper mentions future work on information compression and broader SNN–Transformer applications, but it does not give a deep limitation section. | N3: 0.5 | O3: =F3+H3+J3+L3+N3 -> 4 | P3: Include | Q3: =('Eligible (Safuwan)'!O3+'Eligible (Reeyan)'!O3)/2 -> 4
A4: SpikedAttention: Training-Free and Fully Spike-Driven Transformer-to-SNN Conversion with Winner-Oriented Spike Shift for Softmax Operation | B4: Transformer-to-SNN conversion for image classification and NLP tasks | C4: 2024 | D4: NeurIPS 2024 | E4: The objective is very clear. The paper aims to convert Transformers into fully spike-driven SNNs without changing the attention structure. | F4: 1 | G4: The method is highly detailed. It provides neuron equations, coding schemes, trace-driven matrix multiplication, WOSS softmax, energy formulas, implementation details, and code link. | H4: 1 | I4: The validation is strong. It uses ImageNet, CIFAR-10, CIFAR-100, GLUE, and SQuAD. It compares with several SNN and ANN baselines and reports accuracy, timestep, parameters, and energy. | J4: 1 | K4: The encoding and learning mechanisms are clearly explained. The paper uses one-spike phase coding, binary coding for input, trace-driven matrix multiplication, WOSS softmax, and ANN-to-SNN conversion without training. | L4: 1 | M4: The limitations are clearly stated. The paper says the timestep is still longer than directly trained SNNs and that GeLU and LayerNorm are not yet supported. | N4: 1 | O4: =F4+H4+J4+L4+N4 -> 5 | P4: Include | Q4: =('Eligible (Safuwan)'!O4+'Eligible (Reeyan)'!O4)/2 -> 5
A5: C-Transformer: An Energy-Efficient Homogeneous DNN-Transformer/SNN-Transformer Processor for Large Language Models | B5: Hardware accelerator for DNN–Transformer and SNN–Transformer language models | C5: 2025 | D5: IEEE Journal of Solid-State Circuits | E5: The objective is clear. The paper proposes a C-Transformer chip to reduce computation energy and external memory access for language models. | F5: 1 | G5: The hardware method is well described. It gives chip architecture, HMAU, OSSU, IWGU, ESC, voltage, frequency, SRAM, and benchmark setup. However, RTL, code, and full model training details are not provided. | H5: 1 | I5: The validation is strong. The chip is tested on GPT-2, mT5, T5, and FSMT. It reports energy, latency, perplexity, BLEU, ROUGE-L, and comparison with previous Transformer ASICs. | J5: 1 | K5: The spike encoding is partly explained. The paper uses rate encoding and output spike speculation. However, the learning mechanism and full SNN–Transformer training or conversion process are not deeply specified. | L5: 0.5 | M5: The paper discusses challenges such as memory bottleneck, utilization loss, and EMA energy. However, it does not provide a clear limitations section with future research directions. | N5: 0.5 | O5: =F5+H5+J5+L5+N5 -> 4 | P5: Include | Q5: =('Eligible (Safuwan)'!O5+'Eligible (Reeyan)'!O5)/2 -> 4
A6: Spiking neural P models with dynamic potential reset mechanism for remote sensing image classification | B6: Remote sensing image classification using NSNP-Former and spiking Transformer-like architecture | C6: 2026 | D6: Neurocomputing | E6: The objective is clear. The paper proposes TC-NSNP neurons and NSNP-Former to improve low-latency remote sensing image classification. | F6: 1 | G6: The method is partly reproducible. It gives neuron equations, NSNP-SSA equations, model modules, datasets, data split, optimizer, and framework. However, full hyperparameters, code, and data are not available. | H6: 1 | I6: The validation is moderate to strong. It uses UCM, RSSCN7, and AID datasets and compares with many CNN and SNN baselines. However, it mainly reports accuracy and time step, with limited metrics for energy or efficiency. | J6: 1 | K6: The encoding and learning mechanisms are clearly explained. The paper describes time encoding, TC-NSNP dynamic reset, NSNP-SSA, and direct training with SpikingJelly and PyTorch. | L6: 1 | M6: The paper briefly discusses future work. It suggests extending to segmentation, object detection, cross-modal tasks, more metrics, and lightweight models. Limitations are not deeply discussed. | N6: 0.5 | O6: =F6+H6+J6+L6+N6 -> 4.5 | P6: Include | Q6: =('Eligible (Safuwan)'!O6+'Eligible (Reeyan)'!O6)/2 -> 4
A7: Energy-Efficient Brain-Inspired Self-Attention-Spiking Neural Network Framework for Mix-Type Wafer Defect Recognition | B7: Mixed-type wafer defect recognition using SNN and self-attention | C7: 2025 | D7: IEEE Sensors Journal | E7: The objective is clear. The paper proposes Spiky-SANet to improve wafer defect recognition with low energy use. | F7: 1 | G7: The method is partly reproducible. It gives the model structure, LIF equations, MTS-SA equations, ASL loss, optimizer, dataset split, time step, and GPU setup. However, code and full layer-by-layer settings are not provided. | H7: 0.5 | I7: The validation is strong. It uses the MixedWM38 dataset with 38 defect categories. It reports accuracy, precision, recall, F1-score, α-score, ablation results, confusion matrix, and energy estimation. | J7: 1 | K7: The encoding and learning mechanisms are clearly explained. The paper describes static spiking encoding, spiking convolution, LIF neurons, MTS-SA, surrogate gradient learning, and ASL loss. | L7: 1 | M7: Limitations are not clearly discussed. The paper does not provide a clear limitation section or strong future work direction. | N7: 0 | O7: =F7+H7+J7+L7+N7 -> 3.5 | P7: Include > Borderline | Q7: =('Eligible (Safuwan)'!O7+'Eligible (Reeyan)'!O7)/2 -> 3.5
A8: An Efficient Sparse Hardware Accelerator for Spike-Driven Transformer | B8: Hardware acceleration for Spike-Driven Transformer | C8: 2024 | D8: IEEE Asia-Pacific Conference on Applied Electromagnetics, APACE | E8: The objective is clear. The paper proposes a sparse hardware accelerator for Spike-Driven Transformer to reduce latency and energy. | F8: 0.5 | G8: The method is partly reproducible. It gives the hardware architecture, spike encoding unit, spike maxpooling unit, spike mask-add module, and spike linear unit. However, code, RTL details, and full deployment settings are missing. | H8: 0.5 | I8: The validation is limited. It uses CIFAR-10 and compares with other SNN accelerators. It reports throughput and energy efficiency, but the benchmarking is narrow. | J8: 0.5 | K8: The spike encoding mechanism is clearly described. The paper explains encoded spike positions and LIF neuron equations. However, the learning or training mechanism is not discussed in detail. | L8: 0.5 | M8: Limitations are not discussed. The paper does not provide a clear limitation section or future work direction. | N8: 0 | O8: =F8+H8+J8+L8+N8 -> 2 | P8: Borderline | Q8: =('Eligible (Safuwan)'!O8+'Eligible (Reeyan)'!O8)/2 -> 2.5
A9: Spike-HAR++: An Energy-Efficient and Lightweight Parallel Spiking Transformer for Event-Based Human Action Recognition | B9: Event-based human action recognition using spiking Transformer models | C9: 2024 | D9: Frontiers in Computational Neuroscience | E9: The objective is clear. The paper proposes Spike-HAR and Spike-HAR++ to improve event-based HAR with low energy and lightweight spiking Transformers. | F9: 1 | G9: The method is well described. It gives the model architecture, LIF equations, attention branch, parallel spike-driven Transformer block, training settings, datasets, optimizer, and energy calculation. However, some full layer-level settings and exact code details are not fully shown in the paper. | H9: 0.5 | I9: The validation is strong. It uses SL-Animals-DVS, N-LSA64, DVS128 Gesture, and DailyAction-DVS. It compares with ANN and SNN baselines and reports accuracy, model size, FLOPs/SOPs, power, and ablation results. | J9: 1 | K9: The encoding and learning mechanisms are clearly explained. The paper uses event-frame preprocessing, LIF neurons, spike attention masks, CB-S3A, membrane residual connections, and direct training with SpikingJelly. | L9: 1 | M9: The paper gives a short future direction. It suggests developing larger event-based HAR benchmarks, but limitations are not deeply discussed. | N9: 0.5 | O9: =F9+H9+J9+L9+N9 -> 4 | P9: Include | Q9: =('Eligible (Safuwan)'!O9+'Eligible (Reeyan)'!O9)/2 -> 4
A10: Towards High-Performance Spiking Transformers from ANN to SNN Conversion | B10: ANN-to-SNN conversion for Vision Transformers in image classification | C10: 2024 | D10: ACM Multimedia 2024, MM ’24 | E10: The objective is very clear. The paper aims to convert pretrained Vision Transformers into low-latency and energy-efficient SNNs. | F10: 1 | G10: The method is strong and reproducible. It gives conversion theory, EC modules, Matrix Product-EC, Multi-Threshold neurons, parameter normalization, algorithm steps, experimental settings, and a code link. | H10: 1 | I10: The validation is strong. It uses ImageNet1k, tests ViT-S/16, ViT-B/16, ViT-L/16, and EVA, and compares with direct training, CNN-to-SNN, and Transformer-to-SNN baselines. It reports accuracy, time steps, parameters, and energy ratio. | J10: 1 | K10: The encoding and learning mechanisms are clearly explained. The paper describes ANN-to-SNN conversion, IF neurons, Multi-Threshold neurons, threshold normalization, and expectation compensation for nonlinear Transformer modules. | L10: 1 | M10: The limitations are clearly stated. The paper says the method still needs some multiplication and suggests future work to remove remaining multiplications in nonlinear modules. | N10: 1 | O10: =F10+H10+J10+L10+N10 -> 5 | P10: Include | Q10: =('Eligible (Safuwan)'!O10+'Eligible (Reeyan)'!O10)/2 -> 4.25
A11: A Structured-Sparsity-Based Design Approach for Energy-Efficient Spiking Transformer Processing | B11: Hardware acceleration and sparsity optimization for spiking Transformers | C11: 2026 | D11: IEEE Transactions on Very Large Scale Integration Systems | E11: The objective is clear. The paper aims to improve energy efficiency of spiking Transformer processing by exploiting structured sparsity in SSA blocks. | F11: 1 | G11: The method is partly reproducible. It explains FSSA, neuron filtering, fine-tuning, sparsity-aware dataflow, hardware modules, Verilog RTL synthesis, and simulation setup | H11: 1 | I11: The validation is strong. It tests several spiking Transformer models on ImageNet-1K, CIFAR-10, CIFAR-100, COCO 2017, and ADE20K. It also reports accuracy, sparsity, throughput, energy efficiency, area, and power. | J11: 1 | K11: The spiking mechanism is clearly specified. The paper explains LIF neurons, SSA, FSSA, low-spike-rate neuron filtering, and lightweight fine-tuning. However, it focuses more on hardware sparsity than input spike encoding. | L11: 1 | M11: Limitations are only briefly implied. The paper says more hardware-level research is needed, but it does not provide a clear limitation section or detailed future work. | N11: 0.5 | O11: =F11+H11+J11+L11+N11 -> 4.5 | P11: Include | Q11: =('Eligible (Safuwan)'!O11+'Eligible (Reeyan)'!O11)/2 -> 4
A12: Hardware Efficient Accelerator for Spiking Transformer With Reconfigurable Parallel Time Step Computing | B12: Hardware accelerator for spiking Vision Transformer processing | C12: 2025 | D12: IEEE International Symposium on Circuits and Systems, ISCAS | E12: The objective is clear. The paper proposes Spike-IAND-Former and a hardware accelerator to reduce delay and energy in spiking Transformers. | F12: 1 | G12: The method is partly reproducible. It explains Spike-IAND-Former, IAND residual operation, LIF settings, PE blocks, unrolled LIF neurons, dataflow, Verilog synthesis, and hardware setup. However, code, RTL, and full model details are not provided. | H12: 0.5 | I12: The validation is good. It tests ImageNet and CIFAR-10 and compares with Spikformer and other SNN accelerators. It reports accuracy, throughput, area, SRAM, power, and power efficiency. | J12: 1 | K12: The encoding and spiking mechanisms are partly explained. The paper describes the spiking tokenizer, image-to-spike encoding layer, LIF neurons, IAND operation, and time-step processing. However, the training and surrogate learning method are not deeply explained. | L12: 0.5 | M12: Limitations are not clearly discussed. The paper does not provide a limitation section or detailed future work. | N12: 0 | O12: =F12+H12+J12+L12+N12 -> 3 | P12: Include > Borderline | Q12: =('Eligible (Safuwan)'!O12+'Eligible (Reeyan)'!O12)/2 -> 3.25
A13: Spatial–Temporal Spiking Feature Pruning in Spiking Transformer | B13: Training acceleration and feature pruning for spiking Transformers | C13: 2025 | D13: IEEE Transactions on Cognitive and Developmental Systems | E13: The objective is clear. The paper aims to reduce the training cost of spiking Transformers using spatial and temporal feature pruning. | F13: 1 | G13: The method is well described. It gives LIF equations, Spiking Transformer structure, STSFP equations, Softmatch equations, pseudocode, overhead analysis, pruning ratios, and training settings. However, code availability is not clearly stated. | H13: 0.5 | I13: The validation is strong. It uses CIFAR10-DVS, DVS128 Gesture, N-Caltech 101, CIFAR10, CIFAR100, ImageNet, and object detection testing. It reports accuracy, FLOPs, throughput, GPU memory, training time, and ablation results. | J13: 1 | K13: The spiking and learning mechanisms are clearly explained. The paper describes spike accumulation value, spatial spiking token saliency, temporal spiking feature redundancy, LIF neurons, SSA, STSFP, and Softmatch compensation. | L13: 1 | M13: The paper briefly discusses future work for more complex visual tasks such as object detection. However, it does not provide a clear limitation section. | N13: 0.5 | O13: =F13+H13+J13+L13+N13 -> 4 | P13: Include | Q13: =('Eligible (Safuwan)'!O13+'Eligible (Reeyan)'!O13)/2 -> 4
... A235: Spike Camera Image Reconstruction Based on an Efficient Spiking Transformer | B235: Spike camera image reconstruction using Q-K attention-based Spiking Transformer | C235: 2025 | D235: ACM Multimedia Asia Workshops | E235: The objective is very clear. The paper proposes SIEST to improve spike camera image reconstruction using Q-K spiking attention inside an SNN framework. It directly studies SNN–Transformer integration. | F235: 1 | G235: The method is partly reproducible. It explains spike camera imaging, SNN equations, SIEST architecture, Q-K spiking attention, PFM, loss function, dataset generation, and training settings. However, code and full implementation details are not clearly provided. | H235: 0.5 | I235: The validation is strong. It uses the synthetic SREDS dataset and real-captured spike data. It compares with TFP, TFI, TFSTP, MAHTF, Spk2ImgNet, and SSIR. It reports PSNR, SSIM, LPIPS, NIQE, BRISQUE, CPBD, ablation, visual results, and energy consumption. | J235: 1 | K235: The mechanisms are clear. It explains binary spike streams, membrane-potential propagation, parametric LIF neurons, Q-K spiking attention, spiking MLP, progressive filtering, and spike-to-image reconstruction loss. | L235: 1 | M235: The paper does not clearly discuss limitations. It mentions deployment potential on neuromorphic hardware, but it does not provide a dedicated limitation or future-challenge section. | N235: 0 | O235: =F235+H235+J235+L235+N235 -> 3.5 | P235: Include > Borderline | Q235: =('Eligible (Safuwan)'!O235+'Eligible (Reeyan)'!O235)/2 -> 3.75

Sheet Eligible (Reeyan)
A1: Title | B1: Application | C1: Year | D1: Conference /Journal | E1: Clarity of Objectives & Scope | F1: Score 1 | G1: Methodological Rigor & Reproducibility | H1: Score 2 | I1: Empirical Validation & Benchmarking | J1: Score 3 | K1: Specification of Encoding & Learning Mechanisms | L1: Score 4 | M1: Acknowledgment of Limitations & Open Challenges | N1: Score 5 | O1: Overall Score
A2: Optimizing Spiking Neural Networks with Transformer-Based Spatial Attention | B2: Image classification on static datasets (CIFAR-10/100) | C2: 2024 | D2: 4th International Symposium on Computer Technology and Information Science (ISCTIS) | E2: Clear goals for SNN-Transformer integration. TSSA module and scaling factor well-defined. | F2: 1 | G2: Architecture figures and equations provided. Hyperparameters listed. No code or pseudocode shared. Key layer details missing. | H2: 0.5 | I2: Standard datasets used. Top-1 accuracy reported. Multiple baselines compared. Ablation study included. | J2: 1 | K2: LIF neuron model explained. Scaling factor derivation detailed. Input encoding strategy for static images not explicit. | L2: 0.5 | M2: Hardware and training challenges briefly noted. Future work mentioned. No deep limitation analysis. | N2: 0.5 | O2: =N2+L2+J2+H2+F2 -> 3.5
A3: Advanced SpikingYOLOX: Extending Spiking Neural Network on Object Detection with Spike-based Partial Self-Attention and 2D-Spiking Transformer | B3: Object detection on static images (MS-COCO) | C3: 2025 | D3: 33rd ACM International Conference on Multimedia (MM '25) | E3: Clear goals for SNN-based object detection. PSA-SNN and 2D-Spiking Transformer contributions well-defined. | F3: 1 | G3: Architecture diagrams and equations provided. Training details listed. No code or data shared. Some layer specifications missing. | H3: 0.5 | I3: MS-COCO dataset used. Multiple metrics reported. Strong baseline comparisons. Ablation studies included. Power analysis provided. | J3: 1 | K3: LIF neuron model used. RepConv and SDSA mechanisms explained. Input encoding for static images not explicit. Surrogate gradient method implied but not detailed. | L3: 1 | M3: Future work mentions information compression exploration. General efficiency benefits noted. Model limitations and failure cases not deeply analyzed. | N3: 0.5 | O3: =N3+L3+J3+H3+F3 -> 4
A4: SpikedAttention: Training-Free and Fully Spike-Driven Transformer-to-SNN Conversion with Winner-Oriented Spike Shift for Softmax Operation | B4: Image classification (ImageNet, CIFAR-10/100) and NLP tasks (GLUE, SQuAD) | C4: 2024 | D4: 38th Conference on Neural Information Processing Systems (NeurIPS) | E4: Clear goals for training-free transformer-to-SNN conversion. Trace-driven multiplication and WOSS softmax well-defined. | F4: 1 | G4: Architecture equations provided. Hyperparameters listed. Code shared on GitHub. Implementation details complete. | H4: 1 | I4: Standard datasets used. Multiple metrics reported. Strong baselines compared. Ablation studies included. Energy analysis provided. | J4: 1 | K4: LIF neuron model explained. Spike coding schemes detailed. Trace-driven multiplication and WOSS softmax clearly specified. | L4: 1 | M4: Limitations explicitly stated in Section 6. Future work directions suggested. NeurIPS checklist confirms discussion. | N4: 1 | O4: =N4+L4+J4+H4+F4 -> 5
A5: C-Transformer: An Energy-Efficient Homogeneous DNN-Transformer/SNN-Transformer Processor for Large Language Models | B5: Language modeling, translation, summarization on mobile devices (GPT-2, mT5, T5, FSMT) | C5: 2025 | D5: IEEE Journal of Solid-State Circuits, Vol. 60, No. 10 | E5: Clear goals for on-device LLM acceleration. HDSC, OSSU, IWGU contributions well-defined. | F5: 1 | G5: Architecture figures and equations provided. Chip specs detailed. No code or pseudocode shared. Some threshold values missing. | H5: 1 | I5: Standard models tested. Multiple metrics reported. Strong baseline comparisons. Ablation studies included. Power analysis provided. | J5: 1 | K5: LIF model referenced. Rate coding mentioned. HMAU modes explained. Input token-to-spike encoding not explicit. Training method for SNN not detailed. | L5: 0.5 | M5: General limitations noted: timestep, GeLU/LayerNorm support. Future work mentioned. No deep analysis of accuracy gaps or scalability. | N5: 0.5 | O5: =N5+L5+J5+H5+F5 -> 4
A6: Spiking neural P models with dynamic potential reset mechanism for remote sensing image classification | B6: Remote sensing image classification (UCM, RSSCN7, AID datasets) | C6: 2026 | D6: Neurocomputing, Vol. 679 | E6: Clear goals for SNN-Transformer integration in remote sensing. TC-NSNP neuron and NSNP-SSA contributions well-defined. | F6: 1 | G6: Architecture figures and equations provided. Training framework listed. No code or data shared. Some hyperparameter details missing. | H6: 0.5 | I6: Standard remote sensing datasets used. Accuracy metric reported. Multiple baselines compared. Ablation studies included. Convergence analysis provided. | J6: 1 | K6: TC-NSNP neuron dynamics explained with equations. Time encoding strategy mentioned. Input encoding for static images to spikes not explicit. Surrogate gradient use implied but not detailed. | L6: 0.5 | M6: Application scope limitations noted. Future work suggests extension to segmentation and detection. Model-specific limitations and scalability not deeply analyzed. | N6: 0.5 | O6: =N6+L6+J6+H6+F6 -> 3.5
A7: Energy-Efficient Brain-Inspired Self-Attention-Spiking Neural Network Framework for Mix-Type Wafer Defect Recognition | B7: Mix-type wafer defect recognition in semiconductor manufacturing (MixedWM38 dataset) | C7: 2025 | D7: IEEE Sensors Journal, Vol. 25, No. 12 | E7: Clear goals for SNN-based wafer defect detection. Spiky-SANet, MTS-SA, and ASL contributions well-defined. | F7: 1 | G7: Architecture equations provided. Training framework listed. No code or data shared. Some hyperparameter details missing. | H7: 0.5 | I7: MixedWM38 dataset used. Multiple metrics reported. Strong baseline comparisons. Ablation studies included. Power analysis provided. | J7: 1 | K7: LIF model explained. Rate coding mentioned. MTS-SA mechanism detailed. Input encoding for static images not explicit. Surrogate gradient method specified but not deeply detailed. | L7: 0.5 | M7: General limitations noted: timestep, SNN training complexity. Future work mentioned. No deep analysis of accuracy gaps or scalability. | N7: 0.5 | O7: =N7+L7+J7+H7+F7 -> 3.5
A8: An Efficient Sparse Hardware Accelerator for Spike-Driven Transformer | B8: Image classification on CIFAR-10 using Spike-driven Transformer | C8: 2024 | D8: IEEE Asia-Pacific Conference on Applied Electromagnetics (APACE) | E8: Clear goals for hardware acceleration of Spike-driven Transformer. Spike encoding and computational units well-defined. | F8: 0.5 | G8: Architecture diagrams and equations provided. FPGA implementation details listed. No code or pseudocode shared. Some quantization details missing. | H8: 0.5 | I8: CIFAR-10 dataset used. Throughput and energy metrics reported. Comparison with prior SNN accelerators. Ablation studies included. Power analysis provided. | J8: 1 | K8: LIF model referenced. Rate coding mentioned. Spike encoding unit and position encoding explained. Input encoding from static images not explicit. Training method implied but not detailed. | L8: 0.5 | M8: General limitations noted: timestep, hardware constraints. Future work suggests extension to complex tasks. Model-specific limitations not deeply analyzed. | N8: 0.5 | O8: =N8+L8+J8+H8+F8 -> 3
A9: Spike-HAR++: an energy-efficient and lightweight parallel spiking transformer for event-based human action recognition | B9: Event-based human action recognition on DVS datasets (SL-Animals-DVS, N-LSA64, DVS128 Gesture, DailyAction-DVS) | C9: 2024 | D9: Frontiers in Computational Neuroscience | E9: Clear goals for SNN-based event HAR. Parallel spike transformer and spike attention branch contributions well-defined. | F9: 1 | G9: Architecture equations and training details provided. SpikingJelly framework used. Code link mentioned but not fully accessible. Some hyperparameter details missing. | H9: 0.5 | I9: Four standard event-based datasets used. Multiple metrics reported: accuracy, AP, power, model size. Strong baseline comparisons. Ablation studies included. Energy analysis provided. | J9: 1 | K9: LIF neuron model explained with equations. Binary and phase coding mentioned. Input event-to-spike encoding not explicitly detailed. Surrogate gradient implied but not formally specified. | L9: 1 | M9: Application scope limitations noted. Future work suggests larger benchmarks. Model-specific limitations and real-time constraints not deeply analyzed. | N9: 0.5 | O9: =N9+L9+J9+H9+F9 -> 4
A10: Towards High-performance Spiking Transformers from ANN to SNN Conversion | B10: Image classification on ImageNet1k using ViT models (ViT-S/16, ViT-B/16, ViT-L/16, EVA) | C10: 2024 | D10: 32nd ACM International Conference on Multimedia (MM '24) | E10: Clear goals for ANN-to-SNN conversion of Transformers. ECM and MT neuron contributions well-defined. | F10: 1 | G10: Architecture equations and training details provided. SpikingJelly framework used. Code link mentioned but accessibility unclear. Some hyperparameter details missing. | H10: 0.5 | I10: ImageNet1k dataset used. Top-1 accuracy reported. Multiple baselines compared. Ablation studies included. Energy analysis provided. | J10: 1 | K10: LIF neuron model explained. Rate and phase coding mentioned. MT neuron mechanism detailed. Input encoding from static images not explicit. Surrogate gradient specified but not deeply detailed. | L10: 0.5 | M10: Limitations noted: residual multiplications, GeLU/LayerNorm support. Future work mentioned. Model-specific limitations not deeply analyzed. | N10: 0.5 | O10: =N10+L10+J10+H10+F10 -> 3.5
A11: A Structured-Sparsity-Based Design Approach for Energy-Efficient Spiking Transformer Processing | B11: Hardware acceleration for spiking transformers (ImageNet, CIFAR, COCO, ADE20K) | C11: 2026 | D11: IEEE Transactions on Very Large Scale Integration (VLSI) Systems | E11: Clear goals for exploiting structured sparsity in SSA. FSSA operator and neuron filtering contributions well-defined. | F11: 1 | G11: Architecture and algorithm details provided. Hardware synthesis in 28nm reported. No code or RTL shared. Some implementation parameters missing. | H11: 0.5 | I11: Multiple standard datasets used. Accuracy, throughput, and energy metrics reported. Strong baseline comparisons. Ablation studies included. Power analysis provided. | J11: 1 | K11: LIF neuron model explained. FSSA and filtering mechanisms detailed. Input encoding from static images to spikes not explicit. Surrogate gradient method implied but not specified. | L11: 0.5 | M11: General limitations noted: timestep, hardware constraints. Future work suggests extension to other tasks. Model-specific limitations and scalability not deeply analyzed. | N11: 0.5 | O11: =N11+L11+J11+H11+F11 -> 3.5
A12: Hardware Efficient Accelerator for Spiking Transformer With Reconfigurable Parallel Time Step Computing | B12: Image classification on CIFAR-10 using Spike-driven Transformer | C12: 2025 | D12: IEEE International Symposium on Circuits and Systems (ISCAS) | E12: Clear goals for hardware acceleration of Spike-driven Transformer. Spike encoding and computational units well-defined. | F12: 1 | G12: Architecture diagrams and equations provided. FPGA implementation details listed. No code or pseudocode shared. Some quantization details missing. | H12: 0.5 | I12: CIFAR-10 dataset used. Throughput and energy metrics reported. Comparison with prior SNN accelerators. Ablation studies included. Power analysis provided. | J12: 1 | K12: LIF model referenced. Rate coding mentioned. Spike encoding unit and position encoding explained. Input encoding from static images not explicit. Training method implied but not detailed. | L12: 0.5 | M12: General limitations noted: timestep, hardware constraints. Future work suggests extension to complex tasks. Model-specific limitations not deeply analyzed. | N12: 0.5 | O12: =N12+L12+J12+H12+F12 -> 3.5
A13: Spatial–Temporal Spiking Feature Pruning in Spiking Transformer | B13: Image classification and object detection | C13: 2025 | D13: IEEE Transactions on Cognitive and Developmental Systems | E13: Clear goals for training acceleration via feature pruning. STSFP and Softmatch contributions well-defined. | F13: 1 | G13: Algorithm pseudocode provided. Datasets and baselines listed. | H13: 1 | I13: Six standard datasets used. Multiple metrics reported. Strong baseline comparisons. Extensive ablation studies included. Training time analysis provided. | J13: 1 | K13: LIF neuron model explained. SAV calculation and Softmatch mechanism detailed. Input encoding strategy for raw data not explicit. Surrogate gradient use implied but not detailed. | L13: 0.5 | M13: Application limits for 2D convolutional models noted. Performance drops on ImageNet without fine-tuning. Focus remains on training acceleration. Future work suggests inference optimization. | N13: 0.5 | O13: =N13+L13+J13+H13+F13 -> 4
... A15: SimST: Simulation Framework for Energy-Dataflow Co-Optimization in Spike-Driven Transformer | B15: Energy-dataflow co-optimization for Spike-Driven Transformer inference (neuromorphic accelerator design) | C15: 2025 | D15: IEEE 38th International System-on-Chip Conference (SOCC) | E15: Research goals are clear. The paper aims to establish a unified energy evaluation framework for Spike-Driven Transformers. Scope covers four STB operations: MM, BN, LIF, and RES. | F15: 0.5 | G15: Energy modeling equations are detailed. Memory configurations and dataflow strategies are specified. Six-stage computing flow is described. Code sharing is not explicitly mentioned. Some simulator implementation details lack completeness. | H15: 0.5 | I15: ImageNet-scale workloads are used. Energy and latency metrics are reported. Nine dataflow configurations are compared. Validation against prior work shows 4.6% power inconsistency. Task accuracy benchmarks are not included. Comparisons focus on energy rather than classification performance. | J15: 0.5 | K15: LIF neuron dynamics are explained with equations. Spike encoding via tokenization is described. However, the paper focuses on inference, not training. Surrogate gradient learning is not detailed. Encoding strategy for input conversion lacks technical depth. | L15: 0.5 | M15: Limitations are briefly mentioned in conclusion. Future work suggests insights for neuromorphic accelerator design. Deeper discussion of framework constraints or generalizability is missing. | N15: 0.5 | O15: =N15+L15+J15+H15+F15 -> 2.5
A16: VT-SNN: Variable Time-step Spiking Neural Network Based on Uncertainty Measure and Its Application in Brain Disease Diagnosis | B16: Brain disease diagnosis (MRI classification: Parkinson's disease, multiple mental disorders) | C16: 2025 (expected) | D16: MICCAI 2025 (Conference) | E16: Research goals are clear. The paper aims to address fixed time-step limitations in SNNs for heterogeneous MRI data. Scope covers two clinical datasets. | F16: 1 | G16: Architecture details are provided. LIF neurons and SSA equations are included. Hyperparameters and training protocols are specified. Code is shared on GitHub. Some implementation details could be more complete. | H16: 1 | I16: Two real MRI datasets are used. Multiple metrics are reported (ACC, SEN, SPE, F1). Strong baselines are compared. Ablation studies and energy analysis are included. | J16: 1 | K16: Encoding strategy is explained. MRI data is converted to spike form via SFP module. Spike-encoded positional embedding is used. Surrogate gradient learning is implied but not fully detailed. Fisher information and PAC-Bayes loss are described. | L16: 0.5 | M16: Limitations are briefly mentioned in conclusion. Future work is not explicitly discussed. Deeper analysis of constraints is missing. | N16: 0.5 | O16: =N16+L16+J16+H16+F16 -> 4
A17: Pulse transfer learning: Multi-area river ammonia nitrogen prediction with limited data | B17: Water quality prediction (ammonia nitrogen forecasting for irrigation) | C17: 2025 | D17: Expert Systems With Applications | E17: Research goals are clear. The paper aims to predict NH3-N using SNN-LSTM with multi-head attention. Scope covers single and multi-region scenarios in Gansu Province. | F17: 0 | G17: SNN-LSTM architecture with LIF neurons is described. Equations for neuron dynamics are provided. Hyperparameters and training protocols are specified. Data preprocessing uses LGDI algorithm. Code sharing is not explicitly mentioned. Some implementation details lack completeness. | H17: 0.5 | I17: Standard water quality datasets are used. Multiple metrics are reported (MAE, RMSE, R², NSE). Strong baselines are compared including BP, SVR, LSTM, and recent models. Ablation studies across time steps are included. Single and multi-area evaluations are conducted. | J17: 1 | K17: LIF neuron dynamics are explained with differential equations. Multi-head attention integration is described. EWC loss function with Fisher information is detailed. However, spike encoding strategy for continuous water quality values lacks technical detail. Surrogate gradient learning is implied but not fully specified. | L17: 0.5 | M17: Limitations are briefly mentioned in conclusion regarding practical applicability. Future work is not explicitly discussed. Deeper analysis of constraints like data availability or generalizability to other regions is missing. | N17: 0.5 | O17: =N17+L17+J17+H17+F17 -> 2.5
A18: Spatial-Temporal Self-Attention for Asynchronous Spiking Neural Networks | B18: Neuromorphic vision and speech recognition | C18: 2023 | D18: IJCAI 2023 | E18: Research goals are clear. The paper aims to integrate attention mechanisms with SNNs while preserving asynchronous computation. Scope covers vision and speech tasks. | F18: 1 | G18: Architecture details are complete. Equations for neurons and attention are provided. Hyperparameters and training protocols are specified. Code is shared on GitHub. | H18: 1 | I18: Standard neuromorphic and speech datasets are used. Top-1 accuracy is reported. Strong baselines are compared across multiple tables. Ablation studies validate key components. | J18: 1 | K18: Encoding strategy is clearly explained. Event streams are aggregated into fixed frame sequences. Patches are mapped via convolution. Surrogate gradient learning is used for training. LIF neuron dynamics are detailed. | L18: 1 | M18: Limitations are not explicitly discussed. Future work is not mentioned. The conclusion focuses only on summarizing contributions. Deeper analysis of constraints is missing. | N18: 0.5 | O18: =N18+L18+J18+H18+F18 -> 4.5
A19: Auto-Spikformer: Spikformer architecture search | B19: Vision classification and neuromorphic event recognition | C19: 2024 | D19: Frontiers in Neuroscience | E19: Research goals are clear. The paper aims to reduce energy consumption and parameter redundancy. Scope covers transformer blocks and SNN neuron parameters. | F19: 1 | G19: Supernet training and evolutionary search are detailed. Hyperparameters and training protocols are specified. Code sharing is not explicitly mentioned. Some search space boundaries lack full justification. | H19: 0.5 | I19: Standard vision and neuromorphic datasets are used. Accuracy and energy metrics are reported. Strong baselines are compared. Ablation studies validate the search methods. | J19: 1 | K19: LIF neuron dynamics are defined. Surrogate gradient training is specified. DSPS optimizes threshold and decay parameters. Static image encoding into spikes is briefly described. | L19: 1 | M19: Future work suggests testing on larger datasets. Computational costs of supernet training are not discussed. Hardware deployment constraints are missing. | N19: 0.5 | O19: =N19+L19+J19+H19+F19 -> 4
A20: Low-power and lightweight spiking transformer for EEG-based auditory attention detection | B20: EEG-based auditory attention detection (brain-computer interface) | C20: 2025 | D20: Neural Networks | E20: Research goals are clear. The paper aims to develop a binarized spiking Transformer for EEG-based AAD. Scope covers edge device deployment with low power and lightweight design. | F20: 1 | G20: Architecture details are provided. LIF neuron equations and binarization methods are included. Hyperparameters and training protocols are specified. Code sharing is not explicitly mentioned. Some implementation details lack completeness. | H20: 1 | I20: Standard EEG datasets (KUL, DTU) are used. Multiple metrics are reported across decision windows. Strong baselines are compared. Ablation studies validate time steps and model scales. Energy and model size analyses are included. | J20: 1 | K20: EEG encoding via FFT and azimuthal projection is explained. Spiking convolutional layers serve as automatic encoders. Surrogate gradient learning is mentioned. However, spike encoding strategy for continuous EEG values lacks technical detail. | L20: 0.5 | M20: Limitations are briefly mentioned regarding hardware deployment. Future work suggests FPGA platform exploration. Deeper discussion of generalizability across subjects or recording conditions is missing. | N20: 0.5 | O20: =N20+L20+J20+H20+F20 -> 4
A21: Performance Evaluation of Attention Mechanism and Spiking Neural Networks on sMRI Data for Suicide Ideation Assessment | B21: Suicide ideation assessment using structural MRI (depression patients vs. healthy controls) | C21: 2023 | D21: IEEE International Conference on Computing (ICOCO) | E21: Research goals are clear. The paper aims to detect early suicidal ideation risk using a hybrid AM-SNN model. Scope covers sMRI classification for young adults. | F21: 0 | G21: LIF neuron dynamics and ROPE encoding are described. Data preprocessing steps are outlined. However, hyperparameters and training protocols lack detail. Code sharing is not mentioned. Some implementation details are incomplete. | H21: 0.5 | I21: Uses publicly available sMRI datasets. Reports accuracy, sensitivity, specificity, and AUC. Compares with SVM and KNN baselines. However, dataset is very small (80 samples). Limited comparison with modern SNN methods. No ablation studies. | J21: 0.5 | K21: LIF neuron equations are provided. Rank order population encoding is mentioned. Surrogate gradient approach is briefly described. However, attention-SNN integration lacks mathematical formulation. sMRI to spike encoding strategy lacks technical depth. | L21: 0.5 | M21: Dataset size limitation is briefly mentioned. Future work suggests extending to larger datasets and clinical applications. However, limitations discussion is minimal. No deeper analysis of generalizability or model interpretability constraints. | N21: 0.5 | O21: =N21+L21+J21+H21+F21 -> 2
A22: 3D CSFA-UNet: a unified attention-driven deep learning framework for accurate knee MRI segmentation and osteoarthritis severity classification | B22: Knee MRI segmentation and osteoarthritis severity classification (medical imaging/orthopedic diagnostics) | C22: 2026 | D22: Scientific Reports | E22: Research goals are clear. The paper aims to propose a unified framework for joint segmentation and classification of 3D knee MRI. Scope covers Gaussian filtering, CSFA-UNet, ASPP, DSFS, and Spiking Transformer. | F22: 1 | G22: Architecture details are provided. LIF neuron equations are included. Hyperparameters are specified in Table 2. Datasets and preprocessing are described. Code sharing is not explicitly mentioned. Some implementation details like DSFS parameters lack completeness. | H22: 1 | I22: Standard medical imaging datasets are used. Multiple metrics are reported for segmentation and classification. Strong baselines are compared. Ablation studies and cross-validation are included. Statistical testing is performed. Classification uses X-ray data while segmentation uses MRI, creating a modality gap. | J22: 1 | K22: LIF neuron dynamics are explained with differential equations. Spiking Tokenizer with SCNN layers is described. Surrogate gradient learning is mentioned. However, spike encoding strategy for continuous feature conversion lacks technical detail. Spike-aware attention mechanism lacks full mathematical formulation. | L22: 0.5 | M22: Limitations are briefly mentioned regarding dual-path architecture and independent cohorts. Future work suggests extension to other modalities and lightweight designs. Deeper discussion of clinical deployment constraints and generalizability is missing. | N22: 0.5 | O22: =N22+L22+J22+H22+F22 -> 4
A23: Combining aggregated attention and transformer architecture for accurate and efficient performance of Spiking Neural Networks | B23: Image classification and neuromorphic vision tasks (CIFAR-10/100, Tiny-ImageNet, CIFAR10-DVS, DVS128-Gesture) | C23: 2025 | D23: Neural Networks | E23: Research goals are clear. The paper aims to integrate low-power SNNs with high-performance Transformers via the SASA mechanism. Scope covers static and neuromorphic datasets. | F23: 1 | G23: Architecture details are provided. LIF neuron equations and SASA formulations are included. Hyperparameters and training protocols are specified. Code is shared on GitHub. Some aggregation function parameters could be more explicit. | H23: 1 | I23: Standard datasets are used. Multiple metrics are reported including accuracy and energy consumption. Strong baselines are compared. Ablation studies validate key components. Time-step and sequence length analyses are included. | J23: 1 | K23: LIF neuron dynamics are explained. Spike Patch Splitting module is described. Adaptive average pooling for aggregation is mentioned. Surrogate gradient learning is implied but not fully detailed. Spike encoding strategy for continuous values lacks technical depth. | L23: 0.5 | M23: Limitations are briefly mentioned regarding hardware deployment. Future work suggests hardware optimizations and edge device applications. Deeper discussion of generalizability or computational constraints is missing. | N23: 0.5 | O23: =N23+L23+J23+H23+F23 -> 4
A24: Temporal-coded Spiking Transformer | B24: Image classification and neuromorphic vision tasks (CIFAR-10/100, ImageNet, DVS-CIFAR10) | C24: 2025 | D24: ACM International Conference on Multimedia (MM '25) | E24: Research goals are clear. The paper aims to integrate TTFS coding with transformer architecture. Scope covers static and neuromorphic datasets. | F24: 1 | G24: Architecture details are provided. DFT-based neuron equations and tBN/tRC formulations are included. Hyperparameters and training protocols are specified. Code sharing is not explicitly mentioned. Some implementation details lack completeness. | H24: 0.5 | I24: Standard datasets are used. Multiple metrics are reported including accuracy and energy consumption. Strong baselines are compared. Ablation studies validate tBN and tRC components. | J24: 1 | K24: TTFS encoding strategy is explained with Equation (1). DFT-based neuron dynamics are detailed. Surrogate gradient learning is mentioned but not fully specified. Spike encoding strategy for continuous values lacks technical depth. | L24: 1 | M24: Limitations are briefly mentioned regarding hardware deployment. Future work suggests hardware optimizations and edge device applications. Deeper discussion of generalizability or computational constraints is missing. | N24: 0.5 | O24: =N24+L24+J24+H24+F24 -> 4
A25: AutoST: Training-Free Neural Architecture Search for Spiking Transformers | B25: Image classification and neuromorphic vision tasks (CIFAR-10/100, ImageNet, CIFAR10-DVS) | C25: 2024 | D25: ICASSP 2024 (Conference) | E25: Research goals are clear. The paper aims to address the architectural gap in Spiking Transformers derived from ANNs. Proposes AutoST, a training-free NAS method using FLOPs as performance metric. Scope covers static and neuromorphic datasets. | F25: 1 | G25: FLOPs-based metric and search space design are well-defined. Three search spaces (Tiny, Small, Base) with parameter constraints are specified. Evolutionary search algorithm is described. Code, model, and data are released for reproduction. Energy evaluation formulas are provided. Some implementation details like evolutionary search parameters could be more complete. | H25: 0.5 | I25: Standard datasets are used. Multiple metrics are reported including accuracy, energy consumption, parameters, and timesteps. Strong baselines are compared including Spikformer, AutoSNN, and SEW-ResNet. Ablation studies on timesteps and model topology are included. Correlation analysis validates the FLOPs metric. | J25: 1 | K25: LIF neuron dynamics are explained with equations. Spiking Patch Embedding, Spiking Self Attention, and Spiking MLP are described. Training follows Spikformer setup with AdamW optimizer and cosine decay. However, spike encoding strategy for static images lacks technical detail. Surrogate gradient learning is implied but not fully specified. | L25: 0.5 | M25: Limitations are briefly mentioned regarding extending experiments to larger benchmark datasets. Future work is not explicitly discussed. Deeper discussion of constraints like search space limitations or generalizability to other tasks is missing. | N25: 0.5 | O25: =N25+L25+J25+H25+F25 -> 3.5
A26: Power transformer fault diagnosis and condition monitoring using hybrid TDO-SNN technique | B26: Power transformer fault diagnosis (OLTC) | C26: 2024 | D26: International Journal of Hydrogen Energy | E26: Objectives clearly state fault detection using TDO-SNN. Scope focuses on OLTC fault classification. Goals align with accuracy improvement. | F26: 0 | G26: TDO steps are described. SNN architecture lacks detail. Hyperparameters not specified. No code or data shared. | H26: 0.5 | I26: MATLAB implementation reported. Metrics include accuracy, precision, recall. Comparisons with HBO, WHO, PSO. Datasets not standard or public. | J26: 0.5 | K26: TDO optimizes SNN parameters. Encoding strategy not detailed. SNN described with unclear quantum mechanics reference. Learning mechanism lacks technical depth. | L26: 0.5 | M26: Future work mentions accuracy improvement and data quality. Limitations of method not deeply analyzed. Discussion remains brief. | N26: 0.5 | O26: =N26+L26+J26+H26+F26 -> 2
A27: A novel multi-scale salient object detection framework utilizing nonlinear spiking neural P systems | B27: Salient Object Detection (Computer Vision) | C27: 2025 | D27: Neurocomputing | E27: Objectives clearly target multi-scale SOD using NSNP systems. Three innovations are well-defined. Scope aligns with encoder-decoder SOD tasks. | F27: 0.5 | G27: Architecture and hyperparameters documented. ConvSNP equations provided. Code not publicly shared; data available on request only. | H27: 0.5 | I27: Four standard SOD datasets used. Four evaluation metrics reported. Compared with 14 SOTA methods. Ablation studies included. | J27: 1 | K27: ConvSNP mathematical formulation detailed. Loss function specified. Input spike encoding strategy lacks explicit temporal coding details. | L27: 0.5 | M27: Failure cases analyzed (background similarity, small targets). Future work proposes dataset expansion and domain generalization. | N27: 1 | O27: =N27+L27+J27+H27+F27 -> 3.5
A28: Spiking Transformer with Spatial-Temporal Encoding | B28: Audio & Sequence Modeling | C28: 2025 | D28: ICASSP 2025 | E28: Research goals are clearly stated. Scope targets SNN–Transformer fusion. Objectives align with temporal modeling tasks. | F28: 1 | G28: Network architecture is documented. Key hyperparameters are listed. Public code repository is absent. | H28: 0.5 | I28: Standard academic datasets are used. Multiple performance metrics are reported. Baseline comparisons are thorough. | J28: 1 | K28: Spatial-temporal encoding is clearly defined. Spiking learning rules are detailed. Training procedures are transparent. | L28: 1 | M28: Limitations are briefly summarized. Computational costs are noted. Future hardware deployment is suggested. | N28: 0.5 | O28: =N28+L28+J28+H28+F28 -> 4
... A235: Spike Camera Image Reconstruction Based on an Efficient Spiking Transformer | B235: Spike Camera / Image Reconstruction | C235: 2025 | D235: ACM MMAsia Workshops | E235: Goals clearly target energy-efficient spike camera reconstruction using Q-K attention in SNN architecture. Scope covers SIEST design, sequential spike processing, and evaluation on synthetic and real spike data. | F235: 1 | G235: Architecture and training protocols detailed. Surrogate gradient function specified. Code promised but not yet shared. Some hyperparameter details incomplete. | H235: 0.5 | I235: Uses SREDS and real-captured spike data. Reports PSNR, SSIM, LPIPS, NIQE, BRISQUE, CPBD. Compares TFP, TFI, TFSTP, MAHTF, Spk2ImgNet, SSIR. Includes ablation and energy analysis. | J235: 1 | K235: LIF/PLIF neuron equations and arctan surrogate gradient specified. Q-K attention mechanism detailed. Raw spike-to-token encoding strategy lacks explicit technical depth. | L235: 0.5 | M235: Limitations address dataset scope and neuromorphic deployment needs. Future work suggests hardware validation and task extension. | N235: 1 | O235: =N235+L235+J235+H235+F235 -> 4
